Workbook
Name Beg_Bal: #REF!
Name Cum_Int: #REF!
Name Data: #REF!
Name End_Bal: #REF!
Name Extra_Pay: #REF!
Name Full_Print: #REF!
Name Header_Row: ROW(#REF!)
Name Int: #REF!
Name Interest_Rate: #REF!
Name Last_Row: IF([0]!Values_Entered,Header_Row+[0]!Number_of_Payments,Header_Row)
Name Loan_Amount: #REF!
Name Loan_Start: #REF!
Name Loan_Years: #REF!
Name Num_Pmt_Per_Year: #REF!
Name Number_of_Payments: MATCH(0.01,End_Bal,-1)+1
Name Pay_Date: #REF!
Name Pay_Num: #REF!
Name Payment_Date: DATE(YEAR(Loan_Start),MONTH(Loan_Start)+Payment_Number,DAY(Loan_Start))
Name Princ: #REF!
Name Print_Area_Reset: OFFSET(Full_Print,0,0,Last_Row)
Name Sched_Pay: #REF!
Name Scheduled_Extra_Payments: #REF!
Name Scheduled_Interest_Rate: #REF!
Name Scheduled_Monthly_Payment: #REF!
Name Total_Interest: #REF!
Name Total_Pay: #REF!
Name Values_Entered: IF(Loan_Amount*Interest_Rate*Loan_Years*Loan_Start>0,1,0)
Name zAutoHide4_0335: #REF!

Sheet Merchandise Turnover
B1: Cooperative Bank of Oromia
B4: Customer Name:
B5: Type of Facility
B6: Industry Type
B7: Account Number
B8: Approved Amount
B9: Date Approved
B10: Reporting Date
B13: Month | C13: Debit (Disbursements) | D13: Credit (Principal Repayments)
B26: Total | C26: =SUM(C14:C25) -> 0 | D26: =SUM(D14:D25) -> 0
C28: Prepared by | D28: _____________________

Sheet Pre-Shipment Turnover
B1: Cooperative Bank of Oromia
B4: Customer Name:
B5: Type of Facility
B6: Industry Type
B7: Account Number
B8: Approved Amount
B9: Date Approved
B10: Reporting Date
B13: Month | C13: Debit (Disbursements) | D13: Credit (Principal Repayments)
B26: Total | C26: =SUM(C14:C25) -> 0 | D26: =SUM(D14:D25) -> 0
C28: Prepared by | D28: _____________________

Sheet OD TURNOVER
A2: Turnover Analysis
A3: Account Holder:
A4: Account Number
A5: Industry
A6: Sanction Limit
A7: Approved Date
A8: Facility Type
A9: Report Date:
A10: Status
A12: MONTH | B12: TOTAL TURNOVER CREDIT | C12: TOTAL TURNOVER DEBIT | D12: NUMBER OF CREDIT ENTRY | E12: MONTHELY CREDIT AVG | F12: UTILIZATION PERCENTAGE
B27: Prepared by | C27: _____________________

Sheet OD SWING
A2: Swing Analysis
A3: Account Holder:
A4: Account Number
A5: Industry
A6: Sanction Limit
A7: Approved Date
A8: Facility Type
A9: Report Date:
A10: Status
A12: MONTH | B12: HIGHEST UTILIZATION | C12: DATE HIGH | D12: LOWEST UTILIZATION | E12: DATE LOW | F12: UTILIZATION %
F13: HIGH | G13: LOW
B28: Prepared by | C28: _____________________

Sheet Account Statement
A2: Turnover Analysis
A3: Account Holder:
A4: Account Number
A5: Industry
A6: Sanction Limit
A7: Approved Date
A8: Facility Type
A9: Date Account Opened
A10: Report Date:
A11: Status
A13: MONTH | B13: TOTAL TURNOVER CREDIT | C13: TOTAL TURNOVER DEBIT | D13: NUMBER OF CREDIT ENTRY | E13: MONTHLY CREDIT AVG | F13: UTILIZATION PERCENTAGE
B28: Prepared by | C28: _____________________

Sheet Financial Statement
A1: ABC Company
A2: Balance Sheet as at…
A3: Description | B3: July 07, 2025 G.C | C3: July 7, 2024 G.C | D3: July 7, 2023 G.C | E3: July 7, 2022 G.C | F3: Average
B4: (Audited) | C4: (Audited) | D4: (Audited) | E4: (Audited)
A5: Assets
A6: Non-current assets
A7: Property, plant & equipment | F7: =AVERAGE(B7:E7) -> #DIV/0!
A8: Total Non-current Assets | B8: =SUM(B7) -> 0 | C8: =SUM(C7) -> 0 | D8: =SUM(D7) -> 0 | E8: =SUM(E7) -> 0 | F8: =AVERAGE(B8:E8) -> 0
A9: Current Assets
A10: Stocks | F10: =AVERAGE(B10:E10) -> #DIV/0!
A11: Trade and other receivables | F11: =AVERAGE(B11:E11) -> #DIV/0!
A12: Cash on hand and at bank | F12: =AVERAGE(B12:E12) -> #DIV/0!
A13: Total Current Assets | B13: =SUM(B10:B12) -> 0 | C13: =SUM(C10:C12) -> 0 | D13: =SUM(D10:D12) -> 0 | E13: =SUM(E10:E12) -> 0 | F13: =AVERAGE(B13:E13) -> 0
A14: Total Assets | B14: =B13+B8 -> 0 | C14: =C13+C8 -> 0 | D14: =D13+D8 -> 0 | E14: =E13+E8 -> 0 | F14: =AVERAGE(B14:E14) -> 0
A15: Liabilities
A16: Current Liabilities
A17: Trade & other payables | F17: =AVERAGE(B17:E17) -> #DIV/0!
A18: Other Payables | F18: =AVERAGE(B18:E18) -> #DIV/0!
A19: Shareholder account | F19: =AVERAGE(B19:E19) -> #DIV/0!
A20: Profit tax payable | F20: =AVERAGE(B20:E20) -> #DIV/0!
A21: Total current liability | B21: =SUM(B17:B20) -> 0 | C21: =SUM(C17:C20) -> 0 | D21: =SUM(D17:D20) -> 0 | E21: =SUM(E17:E20) -> 0 | F21: =SUM(F17:F20) -> #DIV/0!
A22: Long term liabilities | B22: =SUM(B23:B24) -> 0 | C22: =SUM(C23:C24) -> 0 | D22: =SUM(D23:D24) -> 0 | E22: =SUM(E23:E24) -> 0 | F22: =SUM(F18:F21) -> #DIV/0!
A23: Bank Loan | F23: =SUM(F19:F22) -> #DIV/0!
A24: Lease payable
A25: Total liabilities | B25: =B21+B22 -> 0 | C25: =C21+C22 -> 0 | D25: =D21+D22 -> 0 | E25: =E21+E22 -> 0 | F25: =F21+F22 -> #DIV/0!
A26: Capital
A27: Capital | F27: =AVERAGE(B27:E27) -> #DIV/0!
A28: Reserve | F28: =AVERAGE(B28:E28) -> #DIV/0!
A29: Retained Earning | F29: =AVERAGE(B29:E29) -> #DIV/0!
A30: Total Capital | B30: =SUM(B27:B29) -> 0 | C30: =SUM(C27:C29) -> 0 | D30: =SUM(D27:D29) -> 0 | E30: =SUM(E27:E29) -> 0 | F30: =SUM(F27:F29) -> #DIV/0!
A31: Total Liability & Capital | B31: =B30+B25 -> 0 | C31: =C30+C25 -> 0 | D31: =D30+D25 -> 0 | E31: =E30+E25 -> 0 | F31: =F30+F25 -> #DIV/0!
A32: Net Working Capital | B32: =B13-B21 -> 0 | C32: =C13-C21 -> 0 | D32: =D13-D21 -> 0 | E32: =E13-E21 -> 0 | F32: =AVERAGE(B32:E32) -> 0
A33: Tangible Net Worth | B33: =B14-B25 -> 0 | C33: =C14-C25 -> 0 | D33: =D14-D25 -> 0 | E33: =E14-E25 -> 0 | F33: =F14-F25 -> #DIV/0!
B34: =B14-B31 -> 0 | C34: =C14-C31 -> 0 | D34: =D14-D31 -> 0 | E34: =E14-E31 -> 0
A36: =A1 -> ABC Company
A37: Income Statement as at …
A38: Description | B38: =B3 -> July 07, 2025 G.C | C38: =C3 -> July 7, 2024 G.C | D38: =D3 -> July 7, 2023 G.C | E38: =E3 -> July 7, 2022 G.C | F38: =F3 -> Average
B39: =B4 -> (Audited) | C39: =C4 -> (Audited) | D39: =D4 -> (Audited) | E39: =E4 -> (Audited)
A40: Sales | F40: =AVERAGE(B40:E40) -> #DIV/0!
A41: Less: Cost of Goods Sold | F41: =AVERAGE(B41:E41) -> #DIV/0!
A42: Gross Profit | B42: =B40-B41 -> 0 | C42: =C40-C41 -> 0 | D42: =D40-D41 -> 0 | E42: =E40-E41 -> 0 | F42: =AVERAGE(B42:E42) -> 0
A43: Less: Operating Expenses | F43: =AVERAGE(B43:E43) -> #DIV/0!
A44: Profit before Interest, tax, and Depreciation | B44: =B42-B43 -> 0 | C44: =C42-C43 -> 0 | D44: =D42-D43 -> 0 | E44: =E42-E43 -> 0 | F44: =AVERAGE(B44:E44) -> 0
A45: Less: Depreciation Expense | F45: =AVERAGE(B45:E45) -> #DIV/0!
A46: Proft Before Interest and Tax | B46: =B44-B45 -> 0 | C46: =C44-C45 -> 0 | D46: =D44-D45 -> 0 | E46: =E44-E45 -> 0 | F46: =AVERAGE(B46:E46) -> 0
A47: Less: Interest Expense | F47: =AVERAGE(B47:E47) -> #DIV/0!
A48: Less: Income tax | B48: =(B46-B47)*35% -> 0 | C48: =(C46-C47)*35% -> 0 | D48: =(D46-D47)*35% -> 0 | E48: =(E46-E47)*35% -> 0 | F48: =AVERAGE(B48:E48) -> 0
A49: Net Income (Net Loss) | B49: =B46-B47-B48 -> 0 | C49: =C46-C47-C48 -> 0 | D49: =D46-D47-D48 -> 0 | E49: =E46-E47-E48 -> 0 | F49: =AVERAGE(B49:E49) -> 0
A51: Quality of Financial Statement
A52: Discrepancy
A54: Efficiency Ratios: | B54: =B38 -> July 07, 2025 G.C | C54: =C38 -> July 7, 2024 G.C | D54: =D38 -> July 7, 2023 G.C | E54: =E38 -> July 7, 2022 G.C | F54: =F38 -> Average
A55: Activity Ratio | B55: =(B40-C40)/C40 -> #DIV/0! | C55: =(C40-D40)/D40 -> #DIV/0! | D55: =(D40-E40)/E40 -> #DIV/0! | F55: =AVERAGE(B55:D55) -> #DIV/0!
A56: Inventory Turnover | B56: =(B10/B41) -> #DIV/0! | C56: =(C10/C41) -> #DIV/0! | D56: =(D10/D41) -> #DIV/0! | E56: =(E10/E41) -> #DIV/0! | F56: =AVERAGE(B56:E56) -> #DIV/0!
A57: Collection Period | B57: =(B11/B40)*365 -> #DIV/0! | C57: =(C11/C40)*365 -> #DIV/0! | D57: =(D11/D40)*365 -> #DIV/0! | E57: =(E11/E40)*365 -> #DIV/0! | F57: =AVERAGE(B57:E57) -> #DIV/0!
A58: Working Capital to Sales | B58: =B32/B40 -> #DIV/0! | C58: =C32/C40 -> #DIV/0! | D58: =D32/D40 -> #DIV/0! | E58: =E32/E40 -> #DIV/0! | F58: =AVERAGE(B58:E58) -> #DIV/0!
A59: Financial Strength Ratios:
A60: Current Ratio (CA/CL) | B60: =B13/B21 -> #DIV/0! | C60: =C13/C21 -> #DIV/0! | D60: =D13/D21 -> #DIV/0! | E60: =E13/E21 -> #DIV/0! | F60: =AVERAGE(B60:E60) -> #DIV/0!
A61: Acid test Ratio | B61: =(B13-B10)/B21 -> #DIV/0! | C61: =(C13-C10)/C21 -> #DIV/0! | D61: =(D13-D10)/D21 -> #DIV/0! | E61: =(E13-E10)/E21 -> #DIV/0! | F61: =AVERAGE(B61:E61) -> #DIV/0!
A62: Equity to Total Asset | B62: =B30/B14 -> #DIV/0! | C62: =C30/C14 -> #DIV/0! | D62: =D30/D14 -> #DIV/0! | E62: =E30/E14 -> #DIV/0! | F62: =AVERAGE(B62:E62) -> #DIV/0!
A63: Debt to total asset | B63: =B25/B14 -> #DIV/0! | C63: =C25/C14 -> #DIV/0! | D63: =D25/D14 -> #DIV/0! | E63: =E25/E14 -> #DIV/0! | F63: =AVERAGE(B63:E63) -> #DIV/0!
A64: Debt to total networth | B64: =B25/B33 -> #DIV/0! | C64: =C25/C33 -> #DIV/0! | D64: =D25/D33 -> #DIV/0! | E64: =E25/E33 -> #DIV/0! | F64: =F25/F33 -> #DIV/0!
A65: Profitability Ratios:
A66: ROA | B66: =B49/B14 -> #DIV/0! | C66: =C49/C14 -> #DIV/0! | D66: =D49/D14 -> #DIV/0! | E66: =E49/E14 -> #DIV/0! | F66: =F49/F14 -> #DIV/0!
A67: ROE | B67: =B49/B30 -> #DIV/0! | C67: =C49/C30 -> #DIV/0! | D67: =D49/D30 -> #DIV/0! | E67: =E49/E30 -> #DIV/0! | F67: =AVERAGE(B67:E67) -> #DIV/0!
A68: Debt Service Coverage Ratio | B68: =B49/B47 -> #DIV/0! | C68: =C49/C47 -> #DIV/0! | D68: =D49/D47 -> #DIV/0! | E68: =E49/E47 -> #DIV/0! | F68: =AVERAGE(B68:E68) -> #DIV/0!
A69: Operating profit margin | B69: =B44/B40 -> #DIV/0! | C69: =C44/C40 -> #DIV/0! | D69: =D44/D40 -> #DIV/0! | E69: =E44/E40 -> #DIV/0! | F69: =AVERAGE(B69:E69) -> #DIV/0!
A70: Gross Profit Margin | B70: =B42/B40 -> #DIV/0! | C70: =C42/C40 -> #DIV/0! | D70: =D42/D40 -> #DIV/0! | E70: =E42/E40 -> #DIV/0! | F70: =AVERAGE(B70:E70) -> #DIV/0!
A71: Net Profit Margin | B71: =B49/B40 -> #DIV/0! | C71: =C49/C40 -> #DIV/0! | D71: =D49/D40 -> #DIV/0! | E71: =E49/E40 -> #DIV/0! | F71: =AVERAGE(B71:E71) -> #DIV/0!
B74: Prepared by | C74: _____________________

Sheet Credit Information
B1: Credit Information
C2: Current Exposure with CoopBank
B3: Sr. No | C3: Existing Exposure with CoopBank | D3: Lending Bank | E3: Date Granted | F3: Expiry Date | G3: Credit Product | H3: Amount Granted | I3: Total Current Balance | J3: Status
B4: 1 | C4: Revolving Facility
B14: Total | H14: =SUM(H4:H13) -> 0 | I14: =SUM(I4:I13) -> 0
B15: 2 | C15: Non-Revolving loan
B26: Total | H26: =SUM(H15:H25) -> 0 | I26: =SUM(I15:I25) -> 0
B27: Grand Total Credit | H27: =H26+H14 -> 0 | I27: =I26+I14 -> 0
C29: Current Exposure with Other Bank
B30: Sr. No | C30: Existing Exposure with Other Bank | D30: Lending Bank | E30: Date Granted | F30: Expiry Date | G30: Credit Product | H30: =H3 -> Amount Granted | I30: Total Current Balance | J30: Status
B31: 1 | C31: Revolving Facility
B49: Sub Total | H49: =SUM(H31:H48) -> 0 | I49: =SUM(I31:I48) -> 0
B50: 2 | C50: Non-Revolving loan
B76: Sub Total | H76: =SUM(H50:H75) -> 0 | I76: =SUM(I50:I75) -> 0
B77: Grand Total | H77: =H76+H49 -> 0 | I77: =I76+I49 -> 0
J78: {=IF(OR(J31:J77="Substandard",J31:J77="Doubtful",J31:J77="Loss"),"NPL","")}
C80: Prepared by | D80: _____________________

Sheet Collateral
A3: No | B3: Type of collateral | C3: Year of Manufacturing | D3: Age | E3: Value | F3: Valuation Method | G3: Mandatory Method | H3: Discount Rate | I3: Net Value
A4: 1 | J4: =B4 -> 0
A5: 2 | D5: =YEAR(TODAY())-C5 -> 2026 | G5: =IF(OR(B5='Security Related Factor'!$D$10,B5='Security Related Factor'!$D$11),IF(AND(D5>3,F5="Invoice"),0,1)) -> FALSE | H5: =IF(AND(B5<>'Security Related Factor'!$D$10,B5<>'Security Related Factor'!$D$11,B5<>'Security Related Factor'!$D$15,B5<>'Security Related Factor'!$D$16,B5<>'Security Related Factor'!$D$19),100%, IF(OR(B5='Security Related Factor'!$D$15,B5='Security Related Factor'!$D$16,B5='Security Related Factor'!$D$19),0%, IF(OR(B5='Security Related Factor'!$D$10,B5='Security Related Factor'!$D$11),IF(AND(D5<=1,F5="Invoice"),90%*G5, IF(OR(B5='Security Related Factor'!$D$10,B5='Security Related Factor'!$D$11),IF(AND(D5>1,D5<=3,F5="Invoice"),80%*G5, IF(OR(B5='Security Related Factor'!$D$10,B5='Security Related Factor'!$D$11),IF(AND(D5>4,F5="Invoice"),0%*G5, IF(OR(B5='Security Related Factor'!$D$10,B5='Security Related Factor'!$D$11),IF(AND(D5<=1,F5="Insurance"),80%*G5, IF(OR(B5='Security Related Factor'!$D$10,B5='Security Related Factor'!$D$11),IF(AND(D5>1,D5<=3,F5="Insurance"),70%*G5, IF(OR(B5='Security Related Factor'!$D$10,B5='Security Related Factor'!$D$11),IF(AND(D5>3,D5<=5,F5="Insurance"),60%*G5, IF(OR(B5='Security Related Factor'!$D$10,B5='Security Related Factor'!$D$11),IF(AND(D5>5,D5<=7,F5="Insurance"),50%*G5, IF(OR(B5='Security Related Factor'!$D$10,B5='Security Related Factor'!$D$11),IF(AND(D5>7,D5<=10,F5="Insurance"),40%*G5, IF(OR(B5='Security Related Factor'!$D$10,B5='Security Related Factor'!$D$11),IF(AND(D5>10,D5<=15,F5="Insurance"),25%*G5, IF(OR(B5='Security Related Factor'!$D$10,B5='Security Related Factor'!$D$11),IF(AND(D5>15,F5="Insurance"),0%*G5)))))))))))))))))))))) -> 1 | I5: =IF(B5="","",H5*E5) | J5: =B5 -> 0
A6: 3 | D6: =YEAR(TODAY())-C6 -> 2026 | G6: =IF(OR(B6='Security Related Factor'!$D$10,B6='Security Related Factor'!$D$11),IF(AND(D6>3,F6="Invoice"),0,1)) -> FALSE | H6: =IF(AND(B6<>'Security Related Factor'!$D$10,B6<>'Security Related Factor'!$D$11,B6<>'Security Related Factor'!$D$15,B6<>'Security Related Factor'!$D$16,B6<>'Security Related Factor'!$D$19),100%, IF(OR(B6='Security Related Factor'!$D$15,B6='Security Related Factor'!$D$16,B6='Security Related Factor'!$D$19),0%, IF(OR(B6='Security Related Factor'!$D$10,B6='Security Related Factor'!$D$11),IF(AND(D6<=1,F6="Invoice"),90%*G6, IF(OR(B6='Security Related Factor'!$D$10,B6='Security Related Factor'!$D$11),IF(AND(D6>1,D6<=3,F6="Invoice"),80%*G6, IF(OR(B6='Security Related Factor'!$D$10,B6='Security Related Factor'!$D$11),IF(AND(D6>4,F6="Invoice"),0%*G6, IF(OR(B6='Security Related Factor'!$D$10,B6='Security Related Factor'!$D$11),IF(AND(D6<=1,F6="Insurance"),80%*G6, IF(OR(B6='Security Related Factor'!$D$10,B6='Security Related Factor'!$D$11),IF(AND(D6>1,D6<=3,F6="Insurance"),70%*G6, IF(OR(B6='Security Related Factor'!$D$10,B6='Security Related Factor'!$D$11),IF(AND(D6>3,D6<=5,F6="Insurance"),60%*G6, IF(OR(B6='Security Related Factor'!$D$10,B6='Security Related Factor'!$D$11),IF(AND(D6>5,D6<=7,F6="Insurance"),50%*G6, IF(OR(B6='Security Related Factor'!$D$10,B6='Security Related Factor'!$D$11),IF(AND(D6>7,D6<=10,F6="Insurance"),40%*G6, IF(OR(B6='Security Related Factor'!$D$10,B6='Security Related Factor'!$D$11),IF(AND(D6>10,D6<=15,F6="Insurance"),25%*G6, IF(OR(B6='Security Related Factor'!$D$10,B6='Security Related Factor'!$D$11),IF(AND(D6>15,F6="Insurance"),0%*G6)))))))))))))))))))))) -> 1 | I6: =IF(B6="","",H6*E6) | J6: =B6 -> 0
A7: 4 | D7: =YEAR(TODAY())-C7 -> 2026 | G7: =IF(OR(B7='Security Related Factor'!$D$10,B7='Security Related Factor'!$D$11),IF(AND(D7>3,F7="Invoice"),0,1)) -> FALSE | H7: =IF(AND(B7<>'Security Related Factor'!$D$10,B7<>'Security Related Factor'!$D$11,B7<>'Security Related Factor'!$D$15,B7<>'Security Related Factor'!$D$16,B7<>'Security Related Factor'!$D$19),100%, IF(OR(B7='Security Related Factor'!$D$15,B7='Security Related Factor'!$D$16,B7='Security Related Factor'!$D$19),0%, IF(OR(B7='Security Related Factor'!$D$10,B7='Security Related Factor'!$D$11),IF(AND(D7<=1,F7="Invoice"),90%*G7, IF(OR(B7='Security Related Factor'!$D$10,B7='Security Related Factor'!$D$11),IF(AND(D7>1,D7<=3,F7="Invoice"),80%*G7, IF(OR(B7='Security Related Factor'!$D$10,B7='Security Related Factor'!$D$11),IF(AND(D7>4,F7="Invoice"),0%*G7, IF(OR(B7='Security Related Factor'!$D$10,B7='Security Related Factor'!$D$11),IF(AND(D7<=1,F7="Insurance"),80%*G7, IF(OR(B7='Security Related Factor'!$D$10,B7='Security Related Factor'!$D$11),IF(AND(D7>1,D7<=3,F7="Insurance"),70%*G7, IF(OR(B7='Security Related Factor'!$D$10,B7='Security Related Factor'!$D$11),IF(AND(D7>3,D7<=5,F7="Insurance"),60%*G7, IF(OR(B7='Security Related Factor'!$D$10,B7='Security Related Factor'!$D$11),IF(AND(D7>5,D7<=7,F7="Insurance"),50%*G7, IF(OR(B7='Security Related Factor'!$D$10,B7='Security Related Factor'!$D$11),IF(AND(D7>7,D7<=10,F7="Insurance"),40%*G7, IF(OR(B7='Security Related Factor'!$D$10,B7='Security Related Factor'!$D$11),IF(AND(D7>10,D7<=15,F7="Insurance"),25%*G7, IF(OR(B7='Security Related Factor'!$D$10,B7='Security Related Factor'!$D$11),IF(AND(D7>15,F7="Insurance"),0%*G7)))))))))))))))))))))) -> 1 | I7: =IF(B7="","",H7*E7) | J7: =B7 -> 0
A8: 5 | D8: =YEAR(TODAY())-C8 -> 2026 | G8: =IF(OR(B8='Security Related Factor'!$D$10,B8='Security Related Factor'!$D$11),IF(AND(D8>3,F8="Invoice"),0,1)) -> FALSE | H8: =IF(AND(B8<>'Security Related Factor'!$D$10,B8<>'Security Related Factor'!$D$11,B8<>'Security Related Factor'!$D$15,B8<>'Security Related Factor'!$D$16,B8<>'Security Related Factor'!$D$19),100%, IF(OR(B8='Security Related Factor'!$D$15,B8='Security Related Factor'!$D$16,B8='Security Related Factor'!$D$19),0%, IF(OR(B8='Security Related Factor'!$D$10,B8='Security Related Factor'!$D$11),IF(AND(D8<=1,F8="Invoice"),90%*G8, IF(OR(B8='Security Related Factor'!$D$10,B8='Security Related Factor'!$D$11),IF(AND(D8>1,D8<=3,F8="Invoice"),80%*G8, IF(OR(B8='Security Related Factor'!$D$10,B8='Security Related Factor'!$D$11),IF(AND(D8>4,F8="Invoice"),0%*G8, IF(OR(B8='Security Related Factor'!$D$10,B8='Security Related Factor'!$D$11),IF(AND(D8<=1,F8="Insurance"),80%*G8, IF(OR(B8='Security Related Factor'!$D$10,B8='Security Related Factor'!$D$11),IF(AND(D8>1,D8<=3,F8="Insurance"),70%*G8, IF(OR(B8='Security Related Factor'!$D$10,B8='Security Related Factor'!$D$11),IF(AND(D8>3,D8<=5,F8="Insurance"),60%*G8, IF(OR(B8='Security Related Factor'!$D$10,B8='Security Related Factor'!$D$11),IF(AND(D8>5,D8<=7,F8="Insurance"),50%*G8, IF(OR(B8='Security Related Factor'!$D$10,B8='Security Related Factor'!$D$11),IF(AND(D8>7,D8<=10,F8="Insurance"),40%*G8, IF(OR(B8='Security Related Factor'!$D$10,B8='Security Related Factor'!$D$11),IF(AND(D8>10,D8<=15,F8="Insurance"),25%*G8, IF(OR(B8='Security Related Factor'!$D$10,B8='Security Related Factor'!$D$11),IF(AND(D8>15,F8="Insurance"),0%*G8)))))))))))))))))))))) -> 1 | I8: =IF(B8="","",H8*E8) | J8: =B8 -> 0
A9: 6 | D9: =YEAR(TODAY())-C9 -> 2026 | G9: =IF(OR(B9='Security Related Factor'!$D$10,B9='Security Related Factor'!$D$11),IF(AND(D9>3,F9="Invoice"),0,1)) -> FALSE | H9: =IF(AND(B9<>'Security Related Factor'!$D$10,B9<>'Security Related Factor'!$D$11,B9<>'Security Related Factor'!$D$15,B9<>'Security Related Factor'!$D$16,B9<>'Security Related Factor'!$D$19),100%, IF(OR(B9='Security Related Factor'!$D$15,B9='Security Related Factor'!$D$16,B9='Security Related Factor'!$D$19),0%, IF(OR(B9='Security Related Factor'!$D$10,B9='Security Related Factor'!$D$11),IF(AND(D9<=1,F9="Invoice"),90%*G9, IF(OR(B9='Security Related Factor'!$D$10,B9='Security Related Factor'!$D$11),IF(AND(D9>1,D9<=3,F9="Invoice"),80%*G9, IF(OR(B9='Security Related Factor'!$D$10,B9='Security Related Factor'!$D$11),IF(AND(D9>4,F9="Invoice"),0%*G9, IF(OR(B9='Security Related Factor'!$D$10,B9='Security Related Factor'!$D$11),IF(AND(D9<=1,F9="Insurance"),80%*G9, IF(OR(B9='Security Related Factor'!$D$10,B9='Security Related Factor'!$D$11),IF(AND(D9>1,D9<=3,F9="Insurance"),70%*G9, IF(OR(B9='Security Related Factor'!$D$10,B9='Security Related Factor'!$D$11),IF(AND(D9>3,D9<=5,F9="Insurance"),60%*G9, IF(OR(B9='Security Related Factor'!$D$10,B9='Security Related Factor'!$D$11),IF(AND(D9>5,D9<=7,F9="Insurance"),50%*G9, IF(OR(B9='Security Related Factor'!$D$10,B9='Security Related Factor'!$D$11),IF(AND(D9>7,D9<=10,F9="Insurance"),40%*G9, IF(OR(B9='Security Related Factor'!$D$10,B9='Security Related Factor'!$D$11),IF(AND(D9>10,D9<=15,F9="Insurance"),25%*G9, IF(OR(B9='Security Related Factor'!$D$10,B9='Security Related Factor'!$D$11),IF(AND(D9>15,F9="Insurance"),0%*G9)))))))))))))))))))))) -> 1 | I9: =IF(B9="","",H9*E9) | J9: =B9 -> 0
A10: 7 | D10: =YEAR(TODAY())-C10 -> 2026 | G10: =IF(OR(B10='Security Related Factor'!$D$10,B10='Security Related Factor'!$D$11),IF(AND(D10>3,F10="Invoice"),0,1)) -> FALSE | H10: =IF(AND(B10<>'Security Related Factor'!$D$10,B10<>'Security Related Factor'!$D$11,B10<>'Security Related Factor'!$D$15,B10<>'Security Related Factor'!$D$16,B10<>'Security Related Factor'!$D$19),100%, IF(OR(B10='Security Related Factor'!$D$15,B10='Security Related Factor'!$D$16,B10='Security Related Factor'!$D$19),0%, IF(OR(B10='Security Related Factor'!$D$10,B10='Security Related Factor'!$D$11),IF(AND(D10<=1,F10="Invoice"),90%*G10, IF(OR(B10='Security Related Factor'!$D$10,B10='Security Related Factor'!$D$11),IF(AND(D10>1,D10<=3,F10="Invoice"),80%*G10, IF(OR(B10='Security Related Factor'!$D$10,B10='Security Related Factor'!$D$11),IF(AND(D10>4,F10="Invoice"),0%*G10, IF(OR(B10='Security Related Factor'!$D$10,B10='Security Related Factor'!$D$11),IF(AND(D10<=1,F10="Insurance"),80%*G10, IF(OR(B10='Security Related Factor'!$D$10,B10='Security Related Factor'!$D$11),IF(AND(D10>1,D10<=3,F10="Insurance"),70%*G10, IF(OR(B10='Security Related Factor'!$D$10,B10='Security Related Factor'!$D$11),IF(AND(D10>3,D10<=5,F10="Insurance"),60%*G10, IF(OR(B10='Security Related Factor'!$D$10,B10='Security Related Factor'!$D$11),IF(AND(D10>5,D10<=7,F10="Insurance"),50%*G10, IF(OR(B10='Security Related Factor'!$D$10,B10='Security Related Factor'!$D$11),IF(AND(D10>7,D10<=10,F10="Insurance"),40%*G10, IF(OR(B10='Security Related Factor'!$D$10,B10='Security Related Factor'!$D$11),IF(AND(D10>10,D10<=15,F10="Insurance"),25%*G10, IF(OR(B10='Security Related Factor'!$D$10,B10='Security Related Factor'!$D$11),IF(AND(D10>15,F10="Insurance"),0%*G10)))))))))))))))))))))) -> 1 | I10: =IF(B10="","",H10*E10) | J10: =B10 -> 0
A11: 8 | D11: =YEAR(TODAY())-C11 -> 2026 | G11: =IF(OR(B11='Security Related Factor'!$D$10,B11='Security Related Factor'!$D$11),IF(AND(D11>3,F11="Invoice"),0,1)) -> FALSE | H11: =IF(AND(B11<>'Security Related Factor'!$D$10,B11<>'Security Related Factor'!$D$11,B11<>'Security Related Factor'!$D$15,B11<>'Security Related Factor'!$D$16,B11<>'Security Related Factor'!$D$19),100%, IF(OR(B11='Security Related Factor'!$D$15,B11='Security Related Factor'!$D$16,B11='Security Related Factor'!$D$19),0%, IF(OR(B11='Security Related Factor'!$D$10,B11='Security Related Factor'!$D$11),IF(AND(D11<=1,F11="Invoice"),90%*G11, IF(OR(B11='Security Related Factor'!$D$10,B11='Security Related Factor'!$D$11),IF(AND(D11>1,D11<=3,F11="Invoice"),80%*G11, IF(OR(B11='Security Related Factor'!$D$10,B11='Security Related Factor'!$D$11),IF(AND(D11>4,F11="Invoice"),0%*G11, IF(OR(B11='Security Related Factor'!$D$10,B11='Security Related Factor'!$D$11),IF(AND(D11<=1,F11="Insurance"),80%*G11, IF(OR(B11='Security Related Factor'!$D$10,B11='Security Related Factor'!$D$11),IF(AND(D11>1,D11<=3,F11="Insurance"),70%*G11, IF(OR(B11='Security Related Factor'!$D$10,B11='Security Related Factor'!$D$11),IF(AND(D11>3,D11<=5,F11="Insurance"),60%*G11, IF(OR(B11='Security Related Factor'!$D$10,B11='Security Related Factor'!$D$11),IF(AND(D11>5,D11<=7,F11="Insurance"),50%*G11, IF(OR(B11='Security Related Factor'!$D$10,B11='Security Related Factor'!$D$11),IF(AND(D11>7,D11<=10,F11="Insurance"),40%*G11, IF(OR(B11='Security Related Factor'!$D$10,B11='Security Related Factor'!$D$11),IF(AND(D11>10,D11<=15,F11="Insurance"),25%*G11, IF(OR(B11='Security Related Factor'!$D$10,B11='Security Related Factor'!$D$11),IF(AND(D11>15,F11="Insurance"),0%*G11)))))))))))))))))))))) -> 1 | I11: =IF(B11="","",H11*E11) | J11: =B11 -> 0
A12: 9 | D12: =YEAR(TODAY())-C12 -> 2026 | G12: =IF(OR(B12='Security Related Factor'!$D$10,B12='Security Related Factor'!$D$11),IF(AND(D12>3,F12="Invoice"),0,1)) -> FALSE | H12: =IF(AND(B12<>'Security Related Factor'!$D$10,B12<>'Security Related Factor'!$D$11,B12<>'Security Related Factor'!$D$15,B12<>'Security Related Factor'!$D$16,B12<>'Security Related Factor'!$D$19),100%, IF(OR(B12='Security Related Factor'!$D$15,B12='Security Related Factor'!$D$16,B12='Security Related Factor'!$D$19),0%, IF(OR(B12='Security Related Factor'!$D$10,B12='Security Related Factor'!$D$11),IF(AND(D12<=1,F12="Invoice"),90%*G12, IF(OR(B12='Security Related Factor'!$D$10,B12='Security Related Factor'!$D$11),IF(AND(D12>1,D12<=3,F12="Invoice"),80%*G12, IF(OR(B12='Security Related Factor'!$D$10,B12='Security Related Factor'!$D$11),IF(AND(D12>4,F12="Invoice"),0%*G12, IF(OR(B12='Security Related Factor'!$D$10,B12='Security Related Factor'!$D$11),IF(AND(D12<=1,F12="Insurance"),80%*G12, IF(OR(B12='Security Related Factor'!$D$10,B12='Security Related Factor'!$D$11),IF(AND(D12>1,D12<=3,F12="Insurance"),70%*G12, IF(OR(B12='Security Related Factor'!$D$10,B12='Security Related Factor'!$D$11),IF(AND(D12>3,D12<=5,F12="Insurance"),60%*G12, IF(OR(B12='Security Related Factor'!$D$10,B12='Security Related Factor'!$D$11),IF(AND(D12>5,D12<=7,F12="Insurance"),50%*G12, IF(OR(B12='Security Related Factor'!$D$10,B12='Security Related Factor'!$D$11),IF(AND(D12>7,D12<=10,F12="Insurance"),40%*G12, IF(OR(B12='Security Related Factor'!$D$10,B12='Security Related Factor'!$D$11),IF(AND(D12>10,D12<=15,F12="Insurance"),25%*G12, IF(OR(B12='Security Related Factor'!$D$10,B12='Security Related Factor'!$D$11),IF(AND(D12>15,F12="Insurance"),0%*G12)))))))))))))))))))))) -> 1 | I12: =IF(B12="","",H12*E12) | J12: =B12 -> 0
A13: 10 | D13: =YEAR(TODAY())-C13 -> 2026 | G13: =IF(OR(B13='Security Related Factor'!$D$10,B13='Security Related Factor'!$D$11),IF(AND(D13>3,F13="Invoice"),0,1)) -> FALSE | H13: =IF(AND(B13<>'Security Related Factor'!$D$10,B13<>'Security Related Factor'!$D$11,B13<>'Security Related Factor'!$D$15,B13<>'Security Related Factor'!$D$16,B13<>'Security Related Factor'!$D$19),100%, IF(OR(B13='Security Related Factor'!$D$15,B13='Security Related Factor'!$D$16,B13='Security Related Factor'!$D$19),0%, IF(OR(B13='Security Related Factor'!$D$10,B13='Security Related Factor'!$D$11),IF(AND(D13<=1,F13="Invoice"),90%*G13, IF(OR(B13='Security Related Factor'!$D$10,B13='Security Related Factor'!$D$11),IF(AND(D13>1,D13<=3,F13="Invoice"),80%*G13, IF(OR(B13='Security Related Factor'!$D$10,B13='Security Related Factor'!$D$11),IF(AND(D13>4,F13="Invoice"),0%*G13, IF(OR(B13='Security Related Factor'!$D$10,B13='Security Related Factor'!$D$11),IF(AND(D13<=1,F13="Insurance"),80%*G13, IF(OR(B13='Security Related Factor'!$D$10,B13='Security Related Factor'!$D$11),IF(AND(D13>1,D13<=3,F13="Insurance"),70%*G13, IF(OR(B13='Security Related Factor'!$D$10,B13='Security Related Factor'!$D$11),IF(AND(D13>3,D13<=5,F13="Insurance"),60%*G13, IF(OR(B13='Security Related Factor'!$D$10,B13='Security Related Factor'!$D$11),IF(AND(D13>5,D13<=7,F13="Insurance"),50%*G13, IF(OR(B13='Security Related Factor'!$D$10,B13='Security Related Factor'!$D$11),IF(AND(D13>7,D13<=10,F13="Insurance"),40%*G13, IF(OR(B13='Security Related Factor'!$D$10,B13='Security Related Factor'!$D$11),IF(AND(D13>10,D13<=15,F13="Insurance"),25%*G13, IF(OR(B13='Security Related Factor'!$D$10,B13='Security Related Factor'!$D$11),IF(AND(D13>15,F13="Insurance"),0%*G13)))))))))))))))))))))) -> 1 | I13: =IF(B13="","",H13*E13) | J13: =B13 -> 0
A14: 11 | D14: =YEAR(TODAY())-C14 -> 2026 | G14: =IF(OR(B14='Security Related Factor'!$D$10,B14='Security Related Factor'!$D$11),IF(AND(D14>3,F14="Invoice"),0,1)) -> FALSE | H14: =IF(AND(B14<>'Security Related Factor'!$D$10,B14<>'Security Related Factor'!$D$11,B14<>'Security Related Factor'!$D$15,B14<>'Security Related Factor'!$D$16,B14<>'Security Related Factor'!$D$19),100%, IF(OR(B14='Security Related Factor'!$D$15,B14='Security Related Factor'!$D$16,B14='Security Related Factor'!$D$19),0%, IF(OR(B14='Security Related Factor'!$D$10,B14='Security Related Factor'!$D$11),IF(AND(D14<=1,F14="Invoice"),90%*G14, IF(OR(B14='Security Related Factor'!$D$10,B14='Security Related Factor'!$D$11),IF(AND(D14>1,D14<=3,F14="Invoice"),80%*G14, IF(OR(B14='Security Related Factor'!$D$10,B14='Security Related Factor'!$D$11),IF(AND(D14>4,F14="Invoice"),0%*G14, IF(OR(B14='Security Related Factor'!$D$10,B14='Security Related Factor'!$D$11),IF(AND(D14<=1,F14="Insurance"),80%*G14, IF(OR(B14='Security Related Factor'!$D$10,B14='Security Related Factor'!$D$11),IF(AND(D14>1,D14<=3,F14="Insurance"),70%*G14, IF(OR(B14='Security Related Factor'!$D$10,B14='Security Related Factor'!$D$11),IF(AND(D14>3,D14<=5,F14="Insurance"),60%*G14, IF(OR(B14='Security Related Factor'!$D$10,B14='Security Related Factor'!$D$11),IF(AND(D14>5,D14<=7,F14="Insurance"),50%*G14, IF(OR(B14='Security Related Factor'!$D$10,B14='Security Related Factor'!$D$11),IF(AND(D14>7,D14<=10,F14="Insurance"),40%*G14, IF(OR(B14='Security Related Factor'!$D$10,B14='Security Related Factor'!$D$11),IF(AND(D14>10,D14<=15,F14="Insurance"),25%*G14, IF(OR(B14='Security Related Factor'!$D$10,B14='Security Related Factor'!$D$11),IF(AND(D14>15,F14="Insurance"),0%*G14)))))))))))))))))))))) -> 1 | I14: =IF(B14="","",H14*E14) | J14: =B14 -> 0
A15: 12 | D15: =YEAR(TODAY())-C15 -> 2026 | G15: =IF(OR(B15='Security Related Factor'!$D$10,B15='Security Related Factor'!$D$11),IF(AND(D15>3,F15="Invoice"),0,1)) -> FALSE | H15: =IF(AND(B15<>'Security Related Factor'!$D$10,B15<>'Security Related Factor'!$D$11,B15<>'Security Related Factor'!$D$15,B15<>'Security Related Factor'!$D$16,B15<>'Security Related Factor'!$D$19),100%, IF(OR(B15='Security Related Factor'!$D$15,B15='Security Related Factor'!$D$16,B15='Security Related Factor'!$D$19),0%, IF(OR(B15='Security Related Factor'!$D$10,B15='Security Related Factor'!$D$11),IF(AND(D15<=1,F15="Invoice"),90%*G15, IF(OR(B15='Security Related Factor'!$D$10,B15='Security Related Factor'!$D$11),IF(AND(D15>1,D15<=3,F15="Invoice"),80%*G15, IF(OR(B15='Security Related Factor'!$D$10,B15='Security Related Factor'!$D$11),IF(AND(D15>4,F15="Invoice"),0%*G15, IF(OR(B15='Security Related Factor'!$D$10,B15='Security Related Factor'!$D$11),IF(AND(D15<=1,F15="Insurance"),80%*G15, IF(OR(B15='Security Related Factor'!$D$10,B15='Security Related Factor'!$D$11),IF(AND(D15>1,D15<=3,F15="Insurance"),70%*G15, IF(OR(B15='Security Related Factor'!$D$10,B15='Security Related Factor'!$D$11),IF(AND(D15>3,D15<=5,F15="Insurance"),60%*G15, IF(OR(B15='Security Related Factor'!$D$10,B15='Security Related Factor'!$D$11),IF(AND(D15>5,D15<=7,F15="Insurance"),50%*G15, IF(OR(B15='Security Related Factor'!$D$10,B15='Security Related Factor'!$D$11),IF(AND(D15>7,D15<=10,F15="Insurance"),40%*G15, IF(OR(B15='Security Related Factor'!$D$10,B15='Security Related Factor'!$D$11),IF(AND(D15>10,D15<=15,F15="Insurance"),25%*G15, IF(OR(B15='Security Related Factor'!$D$10,B15='Security Related Factor'!$D$11),IF(AND(D15>15,F15="Insurance"),0%*G15)))))))))))))))))))))) -> 1 | I15: =IF(B15="","",H15*E15) | J15: =B15 -> 0
A16: 13 | D16: =YEAR(TODAY())-C16 -> 2026 | G16: =IF(OR(B16='Security Related Factor'!$D$10,B16='Security Related Factor'!$D$11),IF(AND(D16>3,F16="Invoice"),0,1)) -> FALSE | H16: =IF(AND(B16<>'Security Related Factor'!$D$10,B16<>'Security Related Factor'!$D$11,B16<>'Security Related Factor'!$D$15,B16<>'Security Related Factor'!$D$16,B16<>'Security Related Factor'!$D$19),100%, IF(OR(B16='Security Related Factor'!$D$15,B16='Security Related Factor'!$D$16,B16='Security Related Factor'!$D$19),0%, IF(OR(B16='Security Related Factor'!$D$10,B16='Security Related Factor'!$D$11),IF(AND(D16<=1,F16="Invoice"),90%*G16, IF(OR(B16='Security Related Factor'!$D$10,B16='Security Related Factor'!$D$11),IF(AND(D16>1,D16<=3,F16="Invoice"),80%*G16, IF(OR(B16='Security Related Factor'!$D$10,B16='Security Related Factor'!$D$11),IF(AND(D16>4,F16="Invoice"),0%*G16, IF(OR(B16='Security Related Factor'!$D$10,B16='Security Related Factor'!$D$11),IF(AND(D16<=1,F16="Insurance"),80%*G16, IF(OR(B16='Security Related Factor'!$D$10,B16='Security Related Factor'!$D$11),IF(AND(D16>1,D16<=3,F16="Insurance"),70%*G16, IF(OR(B16='Security Related Factor'!$D$10,B16='Security Related Factor'!$D$11),IF(AND(D16>3,D16<=5,F16="Insurance"),60%*G16, IF(OR(B16='Security Related Factor'!$D$10,B16='Security Related Factor'!$D$11),IF(AND(D16>5,D16<=7,F16="Insurance"),50%*G16, IF(OR(B16='Security Related Factor'!$D$10,B16='Security Related Factor'!$D$11),IF(AND(D16>7,D16<=10,F16="Insurance"),40%*G16, IF(OR(B16='Security Related Factor'!$D$10,B16='Security Related Factor'!$D$11),IF(AND(D16>10,D16<=15,F16="Insurance"),25%*G16, IF(OR(B16='Security Related Factor'!$D$10,B16='Security Related Factor'!$D$11),IF(AND(D16>15,F16="Insurance"),0%*G16)))))))))))))))))))))) -> 1 | I16: =IF(B16="","",H16*E16) | J16: =B16 -> 0
... A37: 34 | D37: =YEAR(TODAY())-C37 -> 2026 | G37: =IF(OR(B37='Security Related Factor'!$D$10,B37='Security Related Factor'!$D$11),IF(AND(D37>3,F37="Invoice"),0,1)) -> FALSE | H37: =IF(AND(B37<>'Security Related Factor'!$D$10,B37<>'Security Related Factor'!$D$11,B37<>'Security Related Factor'!$D$15,B37<>'Security Related Factor'!$D$16,B37<>'Security Related Factor'!$D$19),100%, IF(OR(B37='Security Related Factor'!$D$15,B37='Security Related Factor'!$D$16,B37='Security Related Factor'!$D$19),0%, IF(OR(B37='Security Related Factor'!$D$10,B37='Security Related Factor'!$D$11),IF(AND(D37<=1,F37="Invoice"),90%*G37, IF(OR(B37='Security Related Factor'!$D$10,B37='Security Related Factor'!$D$11),IF(AND(D37>1,D37<=3,F37="Invoice"),80%*G37, IF(OR(B37='Security Related Factor'!$D$10,B37='Security Related Factor'!$D$11),IF(AND(D37>4,F37="Invoice"),0%*G37, IF(OR(B37='Security Related Factor'!$D$10,B37='Security Related Factor'!$D$11),IF(AND(D37<=1,F37="Insurance"),80%*G37, IF(OR(B37='Security Related Factor'!$D$10,B37='Security Related Factor'!$D$11),IF(AND(D37>1,D37<=3,F37="Insurance"),70%*G37, IF(OR(B37='Security Related Factor'!$D$10,B37='Security Related Factor'!$D$11),IF(AND(D37>3,D37<=5,F37="Insurance"),60%*G37, IF(OR(B37='Security Related Factor'!$D$10,B37='Security Related Factor'!$D$11),IF(AND(D37>5,D37<=7,F37="Insurance"),50%*G37, IF(OR(B37='Security Related Factor'!$D$10,B37='Security Related Factor'!$D$11),IF(AND(D37>7,D37<=10,F37="Insurance"),40%*G37, IF(OR(B37='Security Related Factor'!$D$10,B37='Security Related Factor'!$D$11),IF(AND(D37>10,D37<=15,F37="Insurance"),25%*G37, IF(OR(B37='Security Related Factor'!$D$10,B37='Security Related Factor'!$D$11),IF(AND(D37>15,F37="Insurance"),0%*G37)))))))))))))))))))))) -> 1 | I37: =IF(B37="","",H37*E37) | J37: =B37 -> 0
I38: =SUM(I4:I37) -> 0
A39: Collateral that shares maximum Percentage | I39: =IF(SUM(I4:I37)=0,"",VLOOKUP(MAX(I4:I37),I4:J37,2,0))
B42: Prepared by | C42: _____________________

Sheet WC - CGS
B1: Working Capital Determination
B2: Cost of Goods Sold Method
B4: Operation Year | C4: ='Financial Statement'!B38 -> July 07, 2025 G.C | D4: ='Financial Statement'!C38 -> July 7, 2024 G.C | E4: ='Financial Statement'!D38 -> July 7, 2023 G.C | F4: ='Financial Statement'!E38 -> July 7, 2022 G.C | G4: Average % Growth
B5: Revenue | C5: ='Financial Statement'!B40 -> 0 | D5: ='Financial Statement'!C40 -> 0 | E5: ='Financial Statement'!D40 -> 0 | F5: ='Financial Statement'!E40 -> 0 | G5: =AVERAGE(C5:F5) -> 0
B6: CGS | C6: ='Financial Statement'!B41 -> 0 | D6: ='Financial Statement'!C41 -> 0 | E6: ='Financial Statement'!D41 -> 0 | F6: ='Financial Statement'!E41 -> 0 | G6: =AVERAGE(C6:F6) -> 0
B7: Expenses | C7: ='Financial Statement'!B43 -> 0 | D7: ='Financial Statement'!C43 -> 0 | E7: ='Financial Statement'!D43 -> 0 | F7: ='Financial Statement'!E43 -> 0 | G7: =AVERAGE(C7:F7) -> 0
B8: CGS to Total Sales | C8: =C6/C5 -> #DIV/0! | D8: =D6/D5 -> #DIV/0! | E8: =E6/E5 -> #DIV/0! | F8: =F6/F5 -> #DIV/0! | G8: =AVERAGE(C8:F8) -> #DIV/0!
B9: Sales growth rate | C9: =(C5-D5)/D5 -> #DIV/0! | D9: =(D5-E5)/E5 -> #DIV/0! | E9: =(E5-F5)/F5 -> #DIV/0! | G9: =AVERAGE(C9:F9) -> #DIV/0!
B10: Expense growth rate | C10: =(C7-D7)/D7 -> #DIV/0! | D10: =(D7-E7)/E7 -> #DIV/0! | E10: =(E7-F7)/F7 -> #DIV/0! | G10: =AVERAGE(C10:F10) -> #DIV/0!
B13: Description | C13: Working Capital
B14: Forcasted Sales Revenue | C14: =G5+G5*G9 -> #DIV/0!
B15: Average CGS to total sales | C15: =G8 -> #DIV/0!
B16: Forecasted CGS | C16: =C15*C14 -> #DIV/0!
B17: Expenses | C17: =G7+G7*G10 -> #DIV/0!
B18: Total Annual Working Capital | C18: =C17+C16 -> #DIV/0!
B19: Working Capital Cycle (months) | C19: ='Data Validation'!C71 -> 0
B20: Working Capital for one cycle | C20: =C18/C19 -> #DIV/0!
B21: Less: Net Current Asset) | C21: ='Financial Statement'!B32 -> 0
B22: Less: Existing Facility with Banks
B23: Net working capital required | C23: =C20-C21-C22 -> #DIV/0!
B26: Prepared by | C26: _____________________

Sheet WC - Cash Flow
B1: Working Capital Determination
B2: Cash Flow Method
B5: Description | C5: Working Capital
B6: Forecasted Annual Cash Inflows
B7: Forecasted Annual Cash Outflows
B8: Total Annual Working Capital | C8: =C7 -> 0
B9: Working Capital Cycle (months) | C9: ='Data Validation'!C71 -> 0
B10: Working Capital for one cycle | C10: =C8/C9 -> #DIV/0!
B11: Less: Net Current Asset) | C11: ='Financial Statement'!B32 -> 0
B12: Less: Existing Facility with Banks
B13: Net working capital required | C13: =C10-C11-C12 -> #DIV/0!
B16: Prepared by | C16: _____________________

Sheet Data Validation
B2: Name of Customer
D3: Justification | E3: Source
B4: Sector
B5: Sub-sector
B6: Line of business
B7: Amount Requested
B8: Product Requested
A10: 1 | B10: Business/Industry and form of organization
D11: =D3 -> Justification | E11: Source
A12: 1.1 | B12: Business/Industry outlook of the customer
A13: 1.2 | B13: Market competition/market
A14: 1.3 | B14: Form of Organization
A16: 2 | B16: Financial Ratios
B17: ='Business Strength Score'!B5 -> Activity Ratio | C17: ='Financial Statement'!F55 -> #DIV/0!
B18: ='Business Strength Score'!B6 -> Leverage (Total Debt to total asset) | C18: ='Financial Statement'!B63 -> #DIV/0!
B19: ='Business Strength Score'!B7 -> Liquidity (Current Ratio = CA/CL) | C19: ='Financial Statement'!B60 -> #DIV/0!
B20: ='Business Strength Score'!B8 -> Return on Asset =Net Income after tax /Total asset) | C20: ='Financial Statement'!B66 -> #DIV/0!
B21: ='Business Strength Score'!B9 -> Operating profit Margin(Operating profit/Total Sales) | C21: ='Financial Statement'!B69 -> #DIV/0!
B22: ='Business Strength Score'!B10 -> Debt Service Coverage Ratio (Net income after tax/Interest expenses) | C22: =IF('Financial Statement'!B47="","",'Financial Statement'!B68)
B23: ='Business Strength Score'!B11 -> Inventory Turnover Ratio (CGS/Average Inventory) | C23: ='Financial Statement'!B56 -> #DIV/0!
B24: ='Business Strength Score'!B12 -> Return on Equity (Net Income / Equity) | C24: ='Financial Statement'!B67 -> #DIV/0!
B25: ='Business Strength Score'!B13 -> Quality of Financial Statement | C25: ='Financial Statement'!B51 -> 0
B26: ='Business Strength Score'!B14 -> Negative Values | C26: ='Financial Statement'!B52 -> 0
B27: ='Business Strength Score'!B15 -> Total Equity/Total Asset | C27: ='Financial Statement'!B62 -> #DIV/0!
A28: 3 | B28: Credit History
A29: 2.1 | B29: Loan Facility History | C29: YES
A30: 2.1.1 | B30: Overdraft Utilization | C30: =IF(C31="NO","NO",IF(C29="NO","NO","YES")) -> NO
B31: Overdraft Account Number | C31: =IF(AND(C29="YES",'OD TURNOVER'!B4>0),'OD TURNOVER'!B4,"NO") -> NO
B32: Overdraft Swing (Highest Debit %age) | C32: =IF(C31="NO","NA",-MIN('OD SWING'!B14:B26)/('OD SWING'!B6)) -> NA
B33: Overdraft Swing (Lowest Debit %age) | C33: =IF(C31="NO","NA",-MAX('OD SWING'!D14:D26)/('OD SWING'!B6)) -> NA
B34: Overdraft Turnover | C34: {=IF(C31="NO","NA",SUM('OD TURNOVER'!B13:B25/'OD TURNOVER'!B6))} -> NA
B35: Overdraft Current Status Classifcation | C35: =IF(C30="YES",'OD TURNOVER'!B10,"NA") -> NA
A36: 2.1.2 | B36: Letter of Credit
B37: Average settlement of import L/C facility
A38: 2.1.3 | B38: Merchandise Loan Facility | C38: =IF(C39="NO","NO",IF(C29="NO","NO","YES")) -> NO
B39: Merchandise Loan Account Number | C39: =IF(AND(C29="YES",'Merchandise Turnover'!C7>0),'Merchandise Turnover'!C7,"NO") -> NO
B40: Settlement of Merchandise Loan
B41: Turn-over | C41: {=IF(C38="NO","NA",SUM('Merchandise Turnover'!D14:D26/'Merchandise Turnover'!C8))} -> NA
A42: 2.1.4 | B42: Pre-shipment Export Credit | C42: =IF(C43="NO","NO",IF(C29="NO","NO","YES")) -> NO
B43: Pre-Shipment Loan Account Number | C43: =IF(AND(C29="YES",'Pre-Shipment Turnover'!C7>0),'Pre-Shipment Turnover'!C7,"NO") -> NO
B44: Average settlement from the date of advance in FCY
B45: Turn over | C45: {=IF(C42="NO","NA",SUM('Pre-Shipment Turnover'!D14:D26/'Pre-Shipment Turnover'!C8))} -> NA
A46: 2.1.5 | B46: Post Export Credit facility (ODBP) | C46: NO
B47: ='Data Validation'!B44 -> Average settlement from the date of advance in FCY
A48: 2.1.6 | B48: Guarantee Facility | C48: NO
B49: ='Credit History 29'!C57 -> Settlement of Guarantee
A50: 2.2 | B50: Term Loan Performance
B51: Existing Loan Repayments
B52: Settled Loans
A53: 2.3 | B53: Credit Exposure
B54: Aggregate Credit Exposure
A55: 2.4 | B55: Adverse Classifiation
B56: Adverse Classification Ever
A57: 2.5 | B57: The account transaction to Loan Outstanding with CBO | C57: =IF('Credit Information'!I27=0,"",SUM('Account Statement'!B14:B26)/'Credit Information'!I27)
A58: 4 | B58: Banking Relationship
A59: 3.1 | B59: Length of relationship with CBO | C59: =IF('Account Statement'!B9="","",(TODAY()-'Account Statement'!B9)/365)
A60: 3.2 | B60: The account transaction to sales percentage share with CBO | C60: =IF('Account Statement'!B4="","",SUM('Account Statement'!B14:B26)/'Financial Statement'!B40)
A61: 5 | B61: Character of applicant/management
B62: Consistency of presented document | C62: Adequate
B63: Responsiveness to wards bank's inquiry
B64: Corporate Responsibility (Tax Payment)
A65: 6 | B65: Management Capacity
B66: Experience in related Line of Business
B67: Qualification
B68: Availability of clear duty and Segregation
A69: 7 | B69: Working Capital determination
B70: Working Capital Determination Method to Employ
B71: Working Capital Cycle per Year
B72: Determined Working Capital | C72: =IF(C70="Cost of Good Sold (Trend)",'WC - CGS'!C23,IF(C70="Cash Flow",'WC - Cash Flow'!C13)) -> FALSE
B73: Amount of Working capital to consider | C73: =IF(C72<C7,C72,C7) -> 0
A74: 8 | B74: Collateral | C74: =IF(SUM(Collateral!I4:I37)=0,"NO","YES") -> NO
B75: Collateral Type | C75: =IF(C74="YES",Collateral!I39,"")
B76: Collateral Value | C76: =IF(C74="YES",Collateral!I38,"")
B77: Collateral Coverage Against Request & Existing Oustanding | C77: =IF(C74="YES",C76/C7,"")
B78: Collateral Coverage Against Required Working Capital & Existing Oustanding | C78: =IF(C74="YES",C76/C72,"")
B79: Collateral Coverage Against Considered Working Capital & Existing Oustanding | C79: =IF(C74="YES",C76/C73,"")
C82: Prepared by | D82: _____________________
C83: Revied by | D83: _____________________

Sheet Business Strength Score
A2: Credit Risk Rating and Scoring Template
A4: Perspective | B4: Description | C4: Weight | D4: Score | F4: Mark
A5: Financial (40%) | B5: Activity Ratio | C5: ='Financial 40'!O5 -> 0.03 | D5: =IF(AND('Data Validation'!C4='Financial 40'!C3,'Financial Statement'!F55>='Financial 40'!D5),'Financial 40'!O5, IF(AND('Data Validation'!C4='Financial 40'!C3,'Financial Statement'!F55<'Financial 40'!D6,'Financial Statement'!F55>='Financial 40'!C6),'Financial 40'!O6, IF(AND('Data Validation'!C4='Financial 40'!C3,'Financial Statement'!F55<'Financial 40'!D7,'Financial Statement'!F55>='Financial 40'!C7),'Financial 40'!O7, IF(AND('Data Validation'!C4='Financial 40'!C3,'Financial Statement'!F55<'Financial 40'!D8),'Financial 40'!O8, IF(AND('Data Validation'!C4='Financial 40'!E3,'Financial Statement'!F55>='Financial 40'!F5),'Financial 40'!O5, IF(AND('Data Validation'!C4='Financial 40'!E3,'Financial Statement'!F55<'Financial 40'!F6,'Financial Statement'!F55>='Financial 40'!E6),'Financial 40'!O6, IF(AND('Data Validation'!C4='Financial 40'!E3,'Financial Statement'!F55<'Financial 40'!F7,'Financial Statement'!F55>='Financial 40'!E7),'Financial 40'!O7, IF(AND('Data Validation'!C4='Financial 40'!E3,'Financial Statement'!F55<'Financial 40'!F8),'Financial 40'!O8, IF(AND('Data Validation'!C4='Financial 40'!G3,'Financial Statement'!F55>='Financial 40'!H5),'Financial 40'!O5, IF(AND('Data Validation'!C4='Financial 40'!G3,'Financial Statement'!F55<'Financial 40'!H6,'Financial Statement'!F55>='Financial 40'!G6),'Financial 40'!O6, IF(AND('Data Validation'!C4='Financial 40'!G3,'Financial Statement'!F55<'Financial 40'!H7,'Financial Statement'!F55>='Financial 40'!G7),'Financial 40'!O7, IF(AND('Data Validation'!C4='Financial 40'!G3,'Financial Statement'!F55<'Financial 40'!H8),'Financial 40'!O8, IF(AND('Data Validation'!C4='Financial 40'!I3,'Financial Statement'!F55>='Financial 40'!J5),'Financial 40'!O5, IF(AND('Data Validation'!C4='Financial 40'!I3,'Financial Statement'!F55<'Financial 40'!J6,'Financial Statement'!F55>='Financial 40'!I6),'Financial 40'!O6, IF(AND('Data Validation'!C4='Financial 40'!I3,'Financial Statement'!F55<'Financial 40'!J7,'Financial Statement'!F55>='Financial 40'!I7),'Financial 40'!O7, IF(AND('Data Validation'!C4='Financial 40'!I3,'Financial Statement'!F55<'Financial 40'!J8),'Financial 40'!O8, IF(AND('Data Validation'!C4='Financial 40'!K3,'Financial Statement'!F55>='Financial 40'!L5),'Financial 40'!O5, IF(AND('Data Validation'!C4='Financial 40'!K3,'Financial Statement'!F55<'Financial 40'!L6,'Financial Statement'!F55>='Financial 40'!K6),'Financial 40'!O6, IF(AND('Data Validation'!C4='Financial 40'!K3,'Financial Statement'!F55<'Financial 40'!L7,'Financial Statement'!F55>='Financial 40'!K7),'Financial 40'!O7, IF(AND('Data Validation'!C4='Financial 40'!K3,'Financial Statement'!F55<'Financial 40'!L8),'Financial 40'!O8, IF(AND('Data Validation'!C4='Financial 40'!M3,'Financial Statement'!F55>='Financial 40'!N5),'Financial 40'!O5, IF(AND('Data Validation'!C4='Financial 40'!M3,'Financial Statement'!F55<'Financial 40'!N6,'Financial Statement'!F55>='Financial 40'!M6),'Financial 40'!O6, IF(AND('Data Validation'!C4='Financial 40'!M3,'Financial Statement'!F55<'Financial 40'!N7,'Financial Statement'!F55>='Financial 40'!M7),'Financial 40'!O7, IF(AND('Data Validation'!C4='Financial 40'!M3,'Financial Statement'!F55<'Financial 40'!N8),'Financial 40'!O8)))))))))))))))))))))))) -> #DIV/0! | F5: =SUM(D5:D15) -> #DIV/0!
B6: Leverage (Total Debt to total asset) | C6: ='Financial 40'!O9 -> 0.06 | D6: =IF(AND('Data Validation'!C4='Financial 40'!C3,'Financial Statement'!B63<='Financial 40'!D9),'Financial 40'!O9, IF(AND('Data Validation'!C4='Financial 40'!C3,'Financial Statement'!B63>'Financial 40'!D10,'Financial Statement'!B63<='Financial 40'!C10),'Financial 40'!O10, IF(AND('Data Validation'!C4='Financial 40'!C3,'Financial Statement'!B63>'Financial 40'!D11,'Financial Statement'!B63<='Financial 40'!C11),'Financial 40'!O11, IF(AND('Data Validation'!C4='Financial 40'!C3,'Financial Statement'!B63>'Financial 40'!D12),'Financial 40'!O12, IF(AND('Data Validation'!C4='Financial 40'!E3,'Financial Statement'!B63<='Financial 40'!F9),'Financial 40'!O9, IF(AND('Data Validation'!C4='Financial 40'!E3,'Financial Statement'!B63>'Financial 40'!F10,'Financial Statement'!B63<='Financial 40'!E10),'Financial 40'!O10, IF(AND('Data Validation'!C4='Financial 40'!E3,'Financial Statement'!B63>'Financial 40'!F11,'Financial Statement'!B63<='Financial 40'!E11),'Financial 40'!O11, IF(AND('Data Validation'!C4='Financial 40'!E3,'Financial Statement'!B63>'Financial 40'!F12),'Financial 40'!O12, IF(AND('Data Validation'!C4='Financial 40'!G3,'Financial Statement'!B63<='Financial 40'!H9),'Financial 40'!O9, IF(AND('Data Validation'!C4='Financial 40'!G3,'Financial Statement'!B63>'Financial 40'!H10,'Financial Statement'!B63<='Financial 40'!G10),'Financial 40'!O10, IF(AND('Data Validation'!C4='Financial 40'!G3,'Financial Statement'!B63>'Financial 40'!H11,'Financial Statement'!B63<='Financial 40'!G11),'Financial 40'!O11, IF(AND('Data Validation'!C4='Financial 40'!G3,'Financial Statement'!B63>'Financial 40'!H12),'Financial 40'!O12, IF(AND('Data Validation'!C4='Financial 40'!I3,'Financial Statement'!B63<='Financial 40'!J9),'Financial 40'!O9, IF(AND('Data Validation'!C4='Financial 40'!I3,'Financial Statement'!B63>'Financial 40'!J10,'Financial Statement'!B63<='Financial 40'!I10),'Financial 40'!O10, IF(AND('Data Validation'!C4='Financial 40'!I3,'Financial Statement'!B63>'Financial 40'!J11,'Financial Statement'!B63<='Financial 40'!I11),'Financial 40'!O11, IF(AND('Data Validation'!C4='Financial 40'!I3,'Financial Statement'!B63>'Financial 40'!J12),'Financial 40'!O12, IF(AND('Data Validation'!C4='Financial 40'!K3,'Financial Statement'!B63<='Financial 40'!L9),'Financial 40'!O9, IF(AND('Data Validation'!C4='Financial 40'!K3,'Financial Statement'!B63>'Financial 40'!L10,'Financial Statement'!B63<='Financial 40'!K10),'Financial 40'!O10, IF(AND('Data Validation'!C4='Financial 40'!K3,'Financial Statement'!B63>'Financial 40'!L11,'Financial Statement'!B63<='Financial 40'!K11),'Financial 40'!O11, IF(AND('Data Validation'!C4='Financial 40'!K3,'Financial Statement'!B63>'Financial 40'!L12),'Financial 40'!O12, IF(AND('Data Validation'!C4='Financial 40'!M3,'Financial Statement'!B63<='Financial 40'!N9),'Financial 40'!O9, IF(AND('Data Validation'!C4='Financial 40'!M3,'Financial Statement'!B63>'Financial 40'!N10,'Financial Statement'!B63<='Financial 40'!M10),'Financial 40'!O10, IF(AND('Data Validation'!C4='Financial 40'!M3,'Financial Statement'!B63>'Financial 40'!N11,'Financial Statement'!B63<='Financial 40'!M11),'Financial 40'!O11, IF(AND('Data Validation'!C4='Financial 40'!M3,'Financial Statement'!B63>'Financial 40'!N12),'Financial 40'!O12)))))))))))))))))))))))) -> #DIV/0!
B7: Liquidity (Current Ratio = CA/CL) | C7: ='Financial 40'!O13 -> 0.05 | D7: =IF('Financial Statement'!B21=0,5%, IF(AND('Data Validation'!C4='Financial 40'!C3,'Financial Statement'!B60<='Financial 40'!D13),'Financial 40'!O13, IF(AND('Data Validation'!C4='Financial 40'!C3,'Financial Statement'!B60>'Financial 40'!D14,'Financial Statement'!B60<='Financial 40'!C14),'Financial 40'!O14, IF(AND('Data Validation'!C4='Financial 40'!C3,'Financial Statement'!B60>'Financial 40'!D15,'Financial Statement'!B60<='Financial 40'!C15),'Financial 40'!O15, IF(AND('Data Validation'!C4='Financial 40'!C3,'Financial Statement'!B60>'Financial 40'!D16,'Financial Statement'!B60<='Financial 40'!C16),'Financial 40'!O16, IF(AND('Data Validation'!C4='Financial 40'!C3,'Financial Statement'!B60>'Financial 40'!D17),'Financial 40'!O17, IF(AND('Data Validation'!C4='Financial 40'!E3,'Financial Statement'!B60<='Financial 40'!F13),'Financial 40'!O13, IF(AND('Data Validation'!C4='Financial 40'!E3,'Financial Statement'!B60>'Financial 40'!F14,'Financial Statement'!B60<='Financial 40'!E14),'Financial 40'!O14, IF(AND('Data Validation'!C4='Financial 40'!E3,'Financial Statement'!B60>'Financial 40'!F15,'Financial Statement'!B60<='Financial 40'!E15),'Financial 40'!O15, IF(AND('Data Validation'!C4='Financial 40'!E3,'Financial Statement'!B60>'Financial 40'!F16,'Financial Statement'!B60<='Financial 40'!E16),'Financial 40'!O16, IF(AND('Data Validation'!C4='Financial 40'!E3,'Financial Statement'!B60>'Financial 40'!F17),'Financial 40'!O17, IF(AND('Data Validation'!C4='Financial 40'!G3,'Financial Statement'!B60<='Financial 40'!H13),'Financial 40'!O13, IF(AND('Data Validation'!C4='Financial 40'!G3,'Financial Statement'!B60>'Financial 40'!H14,'Financial Statement'!B60<='Financial 40'!G14),'Financial 40'!O14, IF(AND('Data Validation'!C4='Financial 40'!G3,'Financial Statement'!B60>'Financial 40'!H15,'Financial Statement'!B60<='Financial 40'!G15),'Financial 40'!O15, IF(AND('Data Validation'!C4='Financial 40'!G3,'Financial Statement'!B60>'Financial 40'!H16,'Financial Statement'!B60<='Financial 40'!G16),'Financial 40'!O16, IF(AND('Data Validation'!C4='Financial 40'!G3,'Financial Statement'!B60>'Financial 40'!H17),'Financial 40'!O17, IF(AND('Data Validation'!C4='Financial 40'!I3,'Financial Statement'!B60<='Financial 40'!J13),'Financial 40'!O13, IF(AND('Data Validation'!C4='Financial 40'!I3,'Financial Statement'!B60>'Financial 40'!J14,'Financial Statement'!B60<='Financial 40'!I14),'Financial 40'!O14, IF(AND('Data Validation'!C4='Financial 40'!I3,'Financial Statement'!B60>'Financial 40'!J15,'Financial Statement'!B60<='Financial 40'!I15),'Financial 40'!O15, IF(AND('Data Validation'!C4='Financial 40'!I3,'Financial Statement'!B60>'Financial 40'!J16,'Financial Statement'!B60<='Financial 40'!I16),'Financial 40'!O16, IF(AND('Data Validation'!C4='Financial 40'!I3,'Financial Statement'!B60>'Financial 40'!J17),'Financial 40'!O17, IF(AND('Data Validation'!C4='Financial 40'!K3,'Financial Statement'!B60<='Financial 40'!L13),'Financial 40'!O13, IF(AND('Data Validation'!C4='Financial 40'!K3,'Financial Statement'!B60>'Financial 40'!L14,'Financial Statement'!B60<='Financial 40'!K14),'Financial 40'!O14, IF(AND('Data Validation'!C4='Financial 40'!K3,'Financial Statement'!B60>'Financial 40'!L15,'Financial Statement'!B60<='Financial 40'!K15),'Financial 40'!O15, IF(AND('Data Validation'!C4='Financial 40'!K3,'Financial Statement'!B60>'Financial 40'!L16,'Financial Statement'!B60<='Financial 40'!K16),'Financial 40'!O16, IF(AND('Data Validation'!C4='Financial 40'!K3,'Financial Statement'!B60>'Financial 40'!L17),'Financial 40'!O17, IF(AND('Data Validation'!C4='Financial 40'!M3,'Financial Statement'!B60<='Financial 40'!N13),'Financial 40'!O13, IF(AND('Data Validation'!C4='Financial 40'!M3,'Financial Statement'!B60>'Financial 40'!N14,'Financial Statement'!B60<='Financial 40'!M14),'Financial 40'!O14, IF(AND('Data Validation'!C4='Financial 40'!M3,'Financial Statement'!B60>'Financial 40'!N15,'Financial Statement'!B60<='Financial 40'!M15),'Financial 40'!O15, IF(AND('Data Validation'!C4='Financial 40'!M3,'Financial Statement'!B60>'Financial 40'!N16,'Financial Statement'!B60<='Financial 40'!M16),'Financial 40'!O16, IF(AND('Data Validation'!C4='Financial 40'!M3,'Financial Statement'!B60>'Financial 40'!N17),'Financial 40'!O17))))))))))))))))))))))))))))))) -> 0.05
B8: Return on Asset =Net Income after tax /Total asset) | C8: ='Financial 40'!O19 -> 0.03 | D8: =IF(AND('Data Validation'!C4='Financial 40'!C3,'Financial Statement'!B66>='Financial 40'!D19),'Financial 40'!O19, IF(AND('Data Validation'!C4='Financial 40'!C3,'Financial Statement'!B66<'Financial 40'!D20,'Financial Statement'!B66>='Financial 40'!C20),'Financial 40'!O20, IF(AND('Data Validation'!C4='Financial 40'!C3,'Financial Statement'!B66<'Financial 40'!D21,'Financial Statement'!B66>='Financial 40'!C21),'Financial 40'!O21, IF(AND('Data Validation'!C4='Financial 40'!C3,'Financial Statement'!B66<'Financial 40'!D22,'Financial Statement'!B66>='Financial 40'!C22),'Financial 40'!O22, IF(AND('Data Validation'!C4='Financial 40'!C3,'Financial Statement'!B66<'Financial 40'!D23,'Financial Statement'!B66>='Financial 40'!C23),'Financial 40'!O23, IF(AND('Data Validation'!C4='Financial 40'!C3,'Financial Statement'!B66<'Financial 40'!D24),'Financial 40'!O24, IF(AND('Data Validation'!C4='Financial 40'!E3,'Financial Statement'!B66>='Financial 40'!F19),'Financial 40'!O19, IF(AND('Data Validation'!C4='Financial 40'!E3,'Financial Statement'!B66<'Financial 40'!F20,'Financial Statement'!B66>='Financial 40'!E20),'Financial 40'!O20, IF(AND('Data Validation'!C4='Financial 40'!E3,'Financial Statement'!B66<'Financial 40'!F21,'Financial Statement'!B66>='Financial 40'!E21),'Financial 40'!O21, IF(AND('Data Validation'!C4='Financial 40'!E3,'Financial Statement'!B66<'Financial 40'!F22,'Financial Statement'!B66>='Financial 40'!E22),'Financial 40'!O22, IF(AND('Data Validation'!C4='Financial 40'!E3,'Financial Statement'!B66<'Financial 40'!F23,'Financial Statement'!B66>='Financial 40'!E23),'Financial 40'!O23, IF(AND('Data Validation'!C4='Financial 40'!E3,'Financial Statement'!B66<'Financial 40'!F24),'Financial 40'!O24, IF(AND('Data Validation'!C4='Financial 40'!G3,'Financial Statement'!B66>='Financial 40'!H19),'Financial 40'!O19, IF(AND('Data Validation'!C4='Financial 40'!G3,'Financial Statement'!B66<'Financial 40'!H20,'Financial Statement'!B66>='Financial 40'!G20),'Financial 40'!O20, IF(AND('Data Validation'!C4='Financial 40'!G3,'Financial Statement'!B66<'Financial 40'!H21,'Financial Statement'!B66>='Financial 40'!G21),'Financial 40'!O21, IF(AND('Data Validation'!C4='Financial 40'!G3,'Financial Statement'!B66<'Financial 40'!H22,'Financial Statement'!B66>='Financial 40'!G22),'Financial 40'!O22, IF(AND('Data Validation'!C4='Financial 40'!G3,'Financial Statement'!B66<'Financial 40'!H23,'Financial Statement'!B66>='Financial 40'!G23),'Financial 40'!O23, IF(AND('Data Validation'!C4='Financial 40'!G3,'Financial Statement'!B66<'Financial 40'!H24),'Financial 40'!O24, IF(AND('Data Validation'!C4='Financial 40'!I3,'Financial Statement'!B66>='Financial 40'!J19),'Financial 40'!O19, IF(AND('Data Validation'!C4='Financial 40'!I3,'Financial Statement'!B66<'Financial 40'!J20,'Financial Statement'!B66>='Financial 40'!I20),'Financial 40'!O20, IF(AND('Data Validation'!C4='Financial 40'!I3,'Financial Statement'!B66<'Financial 40'!J21,'Financial Statement'!B66>='Financial 40'!I21),'Financial 40'!O21, IF(AND('Data Validation'!C4='Financial 40'!I3,'Financial Statement'!B66<'Financial 40'!J22,'Financial Statement'!B66>='Financial 40'!I22),'Financial 40'!O22, IF(AND('Data Validation'!C4='Financial 40'!I3,'Financial Statement'!B66<'Financial 40'!J23,'Financial Statement'!B66>='Financial 40'!I23),'Financial 40'!O23, IF(AND('Data Validation'!C4='Financial 40'!I3,'Financial Statement'!B66<'Financial 40'!J24),'Financial 40'!O24, IF(AND('Data Validation'!C4='Financial 40'!K3,'Financial Statement'!B66>='Financial 40'!L19),'Financial 40'!O19, IF(AND('Data Validation'!C4='Financial 40'!K3,'Financial Statement'!B66<'Financial 40'!L20,'Financial Statement'!B66>='Financial 40'!K20),'Financial 40'!O20, IF(AND('Data Validation'!C4='Financial 40'!K3,'Financial Statement'!B66<'Financial 40'!L21,'Financial Statement'!B66>='Financial 40'!K21),'Financial 40'!O21, IF(AND('Data Validation'!C4='Financial 40'!K3,'Financial Statement'!B66<'Financial 40'!L22,'Financial Statement'!B66>='Financial 40'!K22),'Financial 40'!O22, IF(AND('Data Validation'!C4='Financial 40'!K3,'Financial Statement'!B66<'Financial 40'!L23,'Financial Statement'!B66>='Financial 40'!K23),'Financial 40'!O23, IF(AND('Data Validation'!C4='Financial 40'!K3,'Financial Statement'!B66<'Financial 40'!L24),'Financial 40'!O24, IF(AND('Data Validation'!C4='Financial 40'!M3,'Financial Statement'!B66>='Financial 40'!N19),'Financial 40'!O19, IF(AND('Data Validation'!C4='Financial 40'!M3,'Financial Statement'!B66<'Financial 40'!N20,'Financial Statement'!B66>='Financial 40'!M20),'Financial 40'!O20, IF(AND('Data Validation'!C4='Financial 40'!M3,'Financial Statement'!B66<'Financial 40'!N21,'Financial Statement'!B66>='Financial 40'!M21),'Financial 40'!O21, IF(AND('Data Validation'!C4='Financial 40'!M3,'Financial Statement'!B66<'Financial 40'!N22,'Financial Statement'!B66>='Financial 40'!M22),'Financial 40'!O22, IF(AND('Data Validation'!C4='Financial 40'!M3,'Financial Statement'!B66<'Financial 40'!N23,'Financial Statement'!B66>='Financial 40'!M23),'Financial 40'!O23, IF(AND('Data Validation'!C4='Financial 40'!M3,'Financial Statement'!B66<'Financial 40'!N24),'Financial 40'!O24)))))))))))))))))))))))))))))))))))) -> #DIV/0!
B9: Operating profit Margin(Operating profit/Total Sales) | C9: ='Financial 40'!O25 -> 0.05 | D9: =IF(AND('Data Validation'!C4='Financial 40'!C3,'Financial Statement'!B69>='Financial 40'!D25),'Financial 40'!O25, IF(AND('Data Validation'!C4='Financial 40'!C3,'Financial Statement'!B69<'Financial 40'!D26,'Financial Statement'!B69>='Financial 40'!C26),'Financial 40'!O26, IF(AND('Data Validation'!C4='Financial 40'!C3,'Financial Statement'!B69<'Financial 40'!D27,'Financial Statement'!B69>='Financial 40'!C27),'Financial 40'!O27, IF(AND('Data Validation'!C4='Financial 40'!C3,'Financial Statement'!B69<'Financial 40'!D28,'Financial Statement'!B69>='Financial 40'!C28),'Financial 40'!O28, IF(AND('Data Validation'!C4='Financial 40'!C3,'Financial Statement'!B69<'Financial 40'!D29),'Financial 40'!O29, IF(AND('Data Validation'!C4='Financial 40'!E3,'Financial Statement'!B69>='Financial 40'!F25),'Financial 40'!O25, IF(AND('Data Validation'!C4='Financial 40'!E3,'Financial Statement'!B69<'Financial 40'!F26,'Financial Statement'!B69>='Financial 40'!E26),'Financial 40'!O26, IF(AND('Data Validation'!C4='Financial 40'!E3,'Financial Statement'!B69<'Financial 40'!F27,'Financial Statement'!B69>='Financial 40'!E27),'Financial 40'!O27, IF(AND('Data Validation'!C4='Financial 40'!E3,'Financial Statement'!B69<'Financial 40'!F28,'Financial Statement'!B69>='Financial 40'!E28),'Financial 40'!O28, IF(AND('Data Validation'!C4='Financial 40'!E3,'Financial Statement'!B69<'Financial 40'!F29),'Financial 40'!O29, IF(AND('Data Validation'!C4='Financial 40'!G3,'Financial Statement'!B69>='Financial 40'!H25),'Financial 40'!O25, IF(AND('Data Validation'!C4='Financial 40'!G3,'Financial Statement'!B69<'Financial 40'!H26,'Financial Statement'!B69>='Financial 40'!G26),'Financial 40'!O26, IF(AND('Data Validation'!C4='Financial 40'!G3,'Financial Statement'!B69<'Financial 40'!H27,'Financial Statement'!B69>='Financial 40'!G27),'Financial 40'!O27, IF(AND('Data Validation'!C4='Financial 40'!G3,'Financial Statement'!B69<'Financial 40'!H28,'Financial Statement'!B69>='Financial 40'!G28),'Financial 40'!O28, IF(AND('Data Validation'!C4='Financial 40'!G3,'Financial Statement'!B69<'Financial 40'!H29),'Financial 40'!O29, IF(AND('Data Validation'!C4='Financial 40'!I3,'Financial Statement'!B69>='Financial 40'!J25),'Financial 40'!O25, IF(AND('Data Validation'!C4='Financial 40'!I3,'Financial Statement'!B69<'Financial 40'!J26,'Financial Statement'!B69>='Financial 40'!I26),'Financial 40'!O26, IF(AND('Data Validation'!C4='Financial 40'!I3,'Financial Statement'!B69<'Financial 40'!J27,'Financial Statement'!B69>='Financial 40'!I27),'Financial 40'!O27, IF(AND('Data Validation'!C4='Financial 40'!I3,'Financial Statement'!B69<'Financial 40'!J28,'Financial Statement'!B69>='Financial 40'!I28),'Financial 40'!O28, IF(AND('Data Validation'!C4='Financial 40'!I3,'Financial Statement'!B69<'Financial 40'!J29),'Financial 40'!O29, IF(AND('Data Validation'!C4='Financial 40'!K3,'Financial Statement'!B69>='Financial 40'!L25),'Financial 40'!O25, IF(AND('Data Validation'!C4='Financial 40'!K3,'Financial Statement'!B69<'Financial 40'!L26,'Financial Statement'!B69>='Financial 40'!K26),'Financial 40'!O26, IF(AND('Data Validation'!C4='Financial 40'!K3,'Financial Statement'!B69<'Financial 40'!L27,'Financial Statement'!B69>='Financial 40'!K27),'Financial 40'!O27, IF(AND('Data Validation'!C4='Financial 40'!K3,'Financial Statement'!B69<'Financial 40'!L28,'Financial Statement'!B69>='Financial 40'!K28),'Financial 40'!O28, IF(AND('Data Validation'!C4='Financial 40'!K3,'Financial Statement'!B69<'Financial 40'!L29),'Financial 40'!O29, IF(AND('Data Validation'!C4='Financial 40'!M3,'Financial Statement'!B69>='Financial 40'!N25),'Financial 40'!O25, IF(AND('Data Validation'!C4='Financial 40'!M3,'Financial Statement'!B69<'Financial 40'!N26,'Financial Statement'!B69>='Financial 40'!M26),'Financial 40'!O26, IF(AND('Data Validation'!C4='Financial 40'!M3,'Financial Statement'!B69<'Financial 40'!N27,'Financial Statement'!B69>='Financial 40'!M27),'Financial 40'!O27, IF(AND('Data Validation'!C4='Financial 40'!M3,'Financial Statement'!B69<'Financial 40'!N28,'Financial Statement'!B69>='Financial 40'!M28),'Financial 40'!O28, IF(AND('Data Validation'!C4='Financial 40'!M3,'Financial Statement'!B69<'Financial 40'!N29),'Financial 40'!O29)))))))))))))))))))))))))))))) -> #DIV/0!
B10: Debt Service Coverage Ratio (Net income after tax/Interest expenses) | C10: ='Financial 40'!O30 -> 0.03 | D10: =IF('Financial Statement'!B47="",1%, IF(AND('Data Validation'!C4='Financial 40'!C3,'Financial Statement'!B68>='Financial 40'!D30),'Financial 40'!O30, IF(AND('Data Validation'!C4='Financial 40'!C3,'Financial Statement'!B68<'Financial 40'!D31,'Financial Statement'!B68>='Financial 40'!C31),'Financial 40'!O31, IF(AND('Data Validation'!C4='Financial 40'!C3,'Financial Statement'!B68<'Financial 40'!D32,'Financial Statement'!B68>='Financial 40'!C32),'Financial 40'!O32, IF(AND('Data Validation'!C4='Financial 40'!C3,'Financial Statement'!B68<'Financial 40'!D33,'Financial Statement'!B68>='Financial 40'!C33),'Financial 40'!O33, IF(AND('Data Validation'!C4='Financial 40'!C3,'Financial Statement'!B68<'Financial 40'!D34),'Financial 40'!O34, IF(AND('Data Validation'!C4='Financial 40'!E3,'Financial Statement'!B68>='Financial 40'!F30),'Financial 40'!O30, IF(AND('Data Validation'!C4='Financial 40'!E3,'Financial Statement'!B68<'Financial 40'!F31,'Financial Statement'!B68>='Financial 40'!E31),'Financial 40'!O31, IF(AND('Data Validation'!C4='Financial 40'!E3,'Financial Statement'!B68<'Financial 40'!F32,'Financial Statement'!B68>='Financial 40'!E32),'Financial 40'!O32, IF(AND('Data Validation'!C4='Financial 40'!E3,'Financial Statement'!B68<'Financial 40'!F33,'Financial Statement'!B68>='Financial 40'!E33),'Financial 40'!O33, IF(AND('Data Validation'!C4='Financial 40'!E3,'Financial Statement'!B68<'Financial 40'!F34),'Financial 40'!O34, IF(AND('Data Validation'!C4='Financial 40'!G3,'Financial Statement'!B68>='Financial 40'!H30),'Financial 40'!O30, IF(AND('Data Validation'!C4='Financial 40'!G3,'Financial Statement'!B68<'Financial 40'!H31,'Financial Statement'!B68>='Financial 40'!G31),'Financial 40'!O31, IF(AND('Data Validation'!C4='Financial 40'!G3,'Financial Statement'!B68<'Financial 40'!H32,'Financial Statement'!B68>='Financial 40'!G32),'Financial 40'!O32, IF(AND('Data Validation'!C4='Financial 40'!G3,'Financial Statement'!B68<'Financial 40'!H33,'Financial Statement'!B68>='Financial 40'!G33),'Financial 40'!O33, IF(AND('Data Validation'!C4='Financial 40'!G3,'Financial Statement'!B68<'Financial 40'!H34),'Financial 40'!O34, IF(AND('Data Validation'!C4='Financial 40'!I3,'Financial Statement'!B68>='Financial 40'!J30),'Financial 40'!O30, IF(AND('Data Validation'!C4='Financial 40'!I3,'Financial Statement'!B68<'Financial 40'!J31,'Financial Statement'!B68>='Financial 40'!I31),'Financial 40'!O31, IF(AND('Data Validation'!C4='Financial 40'!I3,'Financial Statement'!B68<'Financial 40'!J32,'Financial Statement'!B68>='Financial 40'!I32),'Financial 40'!O32, IF(AND('Data Validation'!C4='Financial 40'!I3,'Financial Statement'!B68<'Financial 40'!J33,'Financial Statement'!B68>='Financial 40'!I33),'Financial 40'!O33, IF(AND('Data Validation'!C4='Financial 40'!I3,'Financial Statement'!B68<'Financial 40'!J34),'Financial 40'!O34, IF(AND('Data Validation'!C4='Financial 40'!K3,'Financial Statement'!B68>='Financial 40'!L30),'Financial 40'!O30, IF(AND('Data Validation'!C4='Financial 40'!K3,'Financial Statement'!B68<'Financial 40'!L31,'Financial Statement'!B68>='Financial 40'!K31),'Financial 40'!O31, IF(AND('Data Validation'!C4='Financial 40'!K3,'Financial Statement'!B68<'Financial 40'!L32,'Financial Statement'!B68>='Financial 40'!K32),'Financial 40'!O32, IF(AND('Data Validation'!C4='Financial 40'!K3,'Financial Statement'!B68<'Financial 40'!L33,'Financial Statement'!B68>='Financial 40'!K33),'Financial 40'!O33, IF(AND('Data Validation'!C4='Financial 40'!K3,'Financial Statement'!B68<'Financial 40'!L34),'Financial 40'!O34, IF(AND('Data Validation'!C4='Financial 40'!M3,'Financial Statement'!B68>='Financial 40'!N30),'Financial 40'!O30, IF(AND('Data Validation'!C4='Financial 40'!M3,'Financial Statement'!B68<'Financial 40'!N31,'Financial Statement'!B68>='Financial 40'!M31),'Financial 40'!O31, IF(AND('Data Validation'!C4='Financial 40'!M3,'Financial Statement'!B68<'Financial 40'!N32,'Financial Statement'!B68>='Financial 40'!M32),'Financial 40'!O32, IF(AND('Data Validation'!C4='Financial 40'!M3,'Financial Statement'!B68<'Financial 40'!N33,'Financial Statement'!B68>='Financial 40'!M33),'Financial 40'!O33, IF(AND('Data Validation'!C4='Financial 40'!M3,'Financial Statement'!B68<'Financial 40'!N34),'Financial 40'!O34))))))))))))))))))))))))))))))) -> 0.01
B11: Inventory Turnover Ratio (CGS/Average Inventory) | C11: ='Financial 40'!O35 -> 0.04 | D11: =IF('Financial Statement'!B10="",4%, IF(AND('Data Validation'!C4='Financial 40'!C3,'Financial Statement'!B56>='Financial 40'!D35),'Financial 40'!O35, IF(AND('Data Validation'!C4='Financial 40'!C3,'Financial Statement'!B56<'Financial 40'!D36,'Financial Statement'!B56>='Financial 40'!C36),'Financial 40'!O36, IF(AND('Data Validation'!C4='Financial 40'!C3,'Financial Statement'!B56<'Financial 40'!D37,'Financial Statement'!B56>='Financial 40'!C37),'Financial 40'!O37, IF(AND('Data Validation'!C4='Financial 40'!C3,'Financial Statement'!B56<'Financial 40'!D39),'Financial 40'!O39, IF(AND('Data Validation'!C4='Financial 40'!E3,'Financial Statement'!B56>='Financial 40'!F35),'Financial 40'!O35, IF(AND('Data Validation'!C4='Financial 40'!E3,'Financial Statement'!B56<'Financial 40'!F36,'Financial Statement'!B56>='Financial 40'!E36),'Financial 40'!O36, IF(AND('Data Validation'!C4='Financial 40'!E3,'Financial Statement'!B56<'Financial 40'!F37,'Financial Statement'!B56>='Financial 40'!E37),'Financial 40'!O37, IF(AND('Data Validation'!C4='Financial 40'!E3,'Financial Statement'!B56<'Financial 40'!F39),'Financial 40'!O39, IF(AND('Data Validation'!C4='Financial 40'!G3,'Financial Statement'!B56>='Financial 40'!H35),'Financial 40'!O35, IF(AND('Data Validation'!C4='Financial 40'!G3,'Financial Statement'!B56<'Financial 40'!H36,'Financial Statement'!B56>='Financial 40'!G36),'Financial 40'!O36, IF(AND('Data Validation'!C4='Financial 40'!G3,'Financial Statement'!B56<'Financial 40'!H37,'Financial Statement'!B56>='Financial 40'!G37),'Financial 40'!O37, IF(AND('Data Validation'!C4='Financial 40'!G3,'Financial Statement'!B56<'Financial 40'!H39),'Financial 40'!O39, IF(AND('Data Validation'!C4='Financial 40'!I3,'Financial Statement'!B56>='Financial 40'!J35),'Financial 40'!O35, IF(AND('Data Validation'!C4='Financial 40'!I3,'Financial Statement'!B56<'Financial 40'!J36,'Financial Statement'!B56>='Financial 40'!I36),'Financial 40'!O36, IF(AND('Data Validation'!C4='Financial 40'!I3,'Financial Statement'!B56<'Financial 40'!J37,'Financial Statement'!B56>='Financial 40'!I37),'Financial 40'!O37, IF(AND('Data Validation'!C4='Financial 40'!I3,'Financial Statement'!B56<'Financial 40'!J39),'Financial 40'!O39, IF(AND('Data Validation'!C4='Financial 40'!K3,'Financial Statement'!B56>='Financial 40'!L35),'Financial 40'!O35, IF(AND('Data Validation'!C4='Financial 40'!K3,'Financial Statement'!B56<'Financial 40'!L36,'Financial Statement'!B56>='Financial 40'!K36),'Financial 40'!O36, IF(AND('Data Validation'!C4='Financial 40'!K3,'Financial Statement'!B56<'Financial 40'!L37,'Financial Statement'!B56>='Financial 40'!K37),'Financial 40'!O37, IF(AND('Data Validation'!C4='Financial 40'!K3,'Financial Statement'!B56<'Financial 40'!L39),'Financial 40'!O39, IF(AND('Data Validation'!C4='Financial 40'!M3,'Financial Statement'!B56>='Financial 40'!N35),'Financial 40'!O35, IF(AND('Data Validation'!C4='Financial 40'!M3,'Financial Statement'!B56<'Financial 40'!N36,'Financial Statement'!B56>='Financial 40'!M36),'Financial 40'!O36, IF(AND('Data Validation'!C4='Financial 40'!M3,'Financial Statement'!B56<'Financial 40'!N37,'Financial Statement'!B56>='Financial 40'!M37),'Financial 40'!O37, IF(AND('Data Validation'!C4='Financial 40'!M3,'Financial Statement'!B56<'Financial 40'!N39),'Financial 40'!O39))))))))))))))))))))))))) -> 0.04
B12: Return on Equity (Net Income / Equity) | C12: ='Financial 40'!O40 -> 0.04 | D12: =IF(AND('Data Validation'!C4='Financial 40'!C3,'Financial Statement'!B67>='Financial 40'!D40),'Financial 40'!O40, IF(AND('Data Validation'!C4='Financial 40'!C3,'Financial Statement'!B67<'Financial 40'!D41,'Financial Statement'!B67>='Financial 40'!C41),'Financial 40'!O41, IF(AND('Data Validation'!C4='Financial 40'!C3,'Financial Statement'!B67<'Financial 40'!D42,'Financial Statement'!B67>='Financial 40'!C42),'Financial 40'!O42, IF(AND('Data Validation'!C4='Financial 40'!C3,'Financial Statement'!B67<'Financial 40'!D43,'Financial Statement'!B67>='Financial 40'!C43),'Financial 40'!O43, IF(AND('Data Validation'!C4='Financial 40'!C3,'Financial Statement'!B67<'Financial 40'!D44),'Financial 40'!O44, IF(AND('Data Validation'!C4='Financial 40'!E3,'Financial Statement'!B67>='Financial 40'!F40),'Financial 40'!O40, IF(AND('Data Validation'!C4='Financial 40'!E3,'Financial Statement'!B67<'Financial 40'!F41,'Financial Statement'!B67>='Financial 40'!E41),'Financial 40'!O41, IF(AND('Data Validation'!C4='Financial 40'!E3,'Financial Statement'!B67<'Financial 40'!F42,'Financial Statement'!B67>='Financial 40'!E42),'Financial 40'!O42, IF(AND('Data Validation'!C4='Financial 40'!E3,'Financial Statement'!B67<'Financial 40'!F43,'Financial Statement'!B67>='Financial 40'!E43),'Financial 40'!O43, IF(AND('Data Validation'!C4='Financial 40'!E3,'Financial Statement'!B67<'Financial 40'!F44),'Financial 40'!O44, IF(AND('Data Validation'!C4='Financial 40'!G3,'Financial Statement'!B67>='Financial 40'!H40),'Financial 40'!O40, IF(AND('Data Validation'!C4='Financial 40'!G3,'Financial Statement'!B67<'Financial 40'!H41,'Financial Statement'!B67>='Financial 40'!G41),'Financial 40'!O41, IF(AND('Data Validation'!C4='Financial 40'!G3,'Financial Statement'!B67<'Financial 40'!H42,'Financial Statement'!B67>='Financial 40'!G42),'Financial 40'!O42, IF(AND('Data Validation'!C4='Financial 40'!G3,'Financial Statement'!B67<'Financial 40'!H43,'Financial Statement'!B67>='Financial 40'!G43),'Financial 40'!O43, IF(AND('Data Validation'!C4='Financial 40'!G3,'Financial Statement'!B67<'Financial 40'!H44),'Financial 40'!O44, IF(AND('Data Validation'!C4='Financial 40'!I3,'Financial Statement'!B67>='Financial 40'!J40),'Financial 40'!O40, IF(AND('Data Validation'!C4='Financial 40'!I3,'Financial Statement'!B67<'Financial 40'!J41,'Financial Statement'!B67>='Financial 40'!I41),'Financial 40'!O41, IF(AND('Data Validation'!C4='Financial 40'!I3,'Financial Statement'!B67<'Financial 40'!J42,'Financial Statement'!B67>='Financial 40'!I42),'Financial 40'!O42, IF(AND('Data Validation'!C4='Financial 40'!I3,'Financial Statement'!B67<'Financial 40'!J43,'Financial Statement'!B67>='Financial 40'!I43),'Financial 40'!O43, IF(AND('Data Validation'!C4='Financial 40'!I3,'Financial Statement'!B67<'Financial 40'!J44),'Financial 40'!O44, IF(AND('Data Validation'!C4='Financial 40'!K3,'Financial Statement'!B67>='Financial 40'!L40),'Financial 40'!O40, IF(AND('Data Validation'!C4='Financial 40'!K3,'Financial Statement'!B67<'Financial 40'!L41,'Financial Statement'!B67>='Financial 40'!K41),'Financial 40'!O41, IF(AND('Data Validation'!C4='Financial 40'!K3,'Financial Statement'!B67<'Financial 40'!L42,'Financial Statement'!B67>='Financial 40'!K42),'Financial 40'!O42, IF(AND('Data Validation'!C4='Financial 40'!K3,'Financial Statement'!B67<'Financial 40'!L43,'Financial Statement'!B67>='Financial 40'!K43),'Financial 40'!O43, IF(AND('Data Validation'!C4='Financial 40'!K3,'Financial Statement'!B67<'Financial 40'!L44),'Financial 40'!O44, IF(AND('Data Validation'!C4='Financial 40'!M3,'Financial Statement'!B67>='Financial 40'!N40),'Financial 40'!O40, IF(AND('Data Validation'!C4='Financial 40'!M3,'Financial Statement'!B67<'Financial 40'!N41,'Financial Statement'!B67>='Financial 40'!M41),'Financial 40'!O41, IF(AND('Data Validation'!C4='Financial 40'!M3,'Financial Statement'!B67<'Financial 40'!N42,'Financial Statement'!B67>='Financial 40'!M42),'Financial 40'!O42, IF(AND('Data Validation'!C4='Financial 40'!M3,'Financial Statement'!B67<'Financial 40'!N43,'Financial Statement'!B67>='Financial 40'!M43),'Financial 40'!O43, IF(AND('Data Validation'!C4='Financial 40'!M3,'Financial Statement'!B67<'Financial 40'!N44),'Financial 40'!O44)))))))))))))))))))))))))))))) -> #DIV/0!
B13: Quality of Financial Statement | C13: ='Financial 40'!O46 -> 0.02 | D13: =IF('Financial Statement'!B51='Financial 40'!C46,'Financial 40'!O46, IF('Financial Statement'!B51='Financial 40'!C47,'Financial 40'!O47, IF('Financial Statement'!B51='Financial 40'!C48,'Financial 40'!O48, IF('Financial Statement'!B51='Financial 40'!C49,'Financial 40'!O49)))) -> FALSE
B14: Negative Values | C14: ='Financial 40'!O52 -> 0 | D14: =IF('Financial Statement'!B52='Financial 40'!C50,'Financial 40'!O50, IF('Financial Statement'!B52='Financial 40'!C51,'Financial 40'!O51, IF('Financial Statement'!B52='Financial 40'!C52,'Financial 40'!O52))) -> FALSE
B15: Total Equity/Total Asset | C15: ='Financial 40'!O53 -> 0.05 | D15: =IF(AND('Data Validation'!C4='Financial 40'!C3,'Financial Statement'!B62>='Financial 40'!D53),'Financial 40'!O53, IF(AND('Data Validation'!C4='Financial 40'!C3,'Financial Statement'!B62<'Financial 40'!D54,'Financial Statement'!B62>='Financial 40'!C54),'Financial 40'!O54, IF(AND('Data Validation'!C4='Financial 40'!C3,'Financial Statement'!B62<'Financial 40'!D55,'Financial Statement'!B62>='Financial 40'!C55),'Financial 40'!O55, IF(AND('Data Validation'!C4='Financial 40'!C3,'Financial Statement'!B62<'Financial 40'!D56,'Financial Statement'!B62>='Financial 40'!C56),'Financial 40'!O56, IF(AND('Data Validation'!C4='Financial 40'!C3,'Financial Statement'!B62<'Financial 40'!D57),'Financial 40'!O57, IF(AND('Data Validation'!C4='Financial 40'!E3,'Financial Statement'!B62>='Financial 40'!F53),'Financial 40'!O53, IF(AND('Data Validation'!C4='Financial 40'!E3,'Financial Statement'!B62<'Financial 40'!F54,'Financial Statement'!B62>='Financial 40'!E54),'Financial 40'!O54, IF(AND('Data Validation'!C4='Financial 40'!E3,'Financial Statement'!B62<'Financial 40'!F55,'Financial Statement'!B62>='Financial 40'!E55),'Financial 40'!O55, IF(AND('Data Validation'!C4='Financial 40'!E3,'Financial Statement'!B62<'Financial 40'!F56,'Financial Statement'!B62>='Financial 40'!E56),'Financial 40'!O56, IF(AND('Data Validation'!C4='Financial 40'!E3,'Financial Statement'!B62<'Financial 40'!F57),'Financial 40'!O57, IF(AND('Data Validation'!C4='Financial 40'!G3,'Financial Statement'!B62>='Financial 40'!H53),'Financial 40'!O53, IF(AND('Data Validation'!C4='Financial 40'!G3,'Financial Statement'!B62<'Financial 40'!H54,'Financial Statement'!B62>='Financial 40'!G54),'Financial 40'!O54, IF(AND('Data Validation'!C4='Financial 40'!G3,'Financial Statement'!B62<'Financial 40'!H55,'Financial Statement'!B62>='Financial 40'!G55),'Financial 40'!O55, IF(AND('Data Validation'!C4='Financial 40'!G3,'Financial Statement'!B62<'Financial 40'!H56,'Financial Statement'!B62>='Financial 40'!G56),'Financial 40'!O56, IF(AND('Data Validation'!C4='Financial 40'!G3,'Financial Statement'!B62<'Financial 40'!H57),'Financial 40'!O57, IF(AND('Data Validation'!C4='Financial 40'!I3,'Financial Statement'!B62>='Financial 40'!J53),'Financial 40'!O53, IF(AND('Data Validation'!C4='Financial 40'!I3,'Financial Statement'!B62<'Financial 40'!J54,'Financial Statement'!B62>='Financial 40'!I54),'Financial 40'!O54, IF(AND('Data Validation'!C4='Financial 40'!I3,'Financial Statement'!B62<'Financial 40'!J55,'Financial Statement'!B62>='Financial 40'!I55),'Financial 40'!O55, IF(AND('Data Validation'!C4='Financial 40'!I3,'Financial Statement'!B62<'Financial 40'!J56,'Financial Statement'!B62>='Financial 40'!I56),'Financial 40'!O56, IF(AND('Data Validation'!C4='Financial 40'!I3,'Financial Statement'!B62<'Financial 40'!J57),'Financial 40'!O57, IF(AND('Data Validation'!C4='Financial 40'!K3,'Financial Statement'!B62>='Financial 40'!L53),'Financial 40'!O53, IF(AND('Data Validation'!C4='Financial 40'!K3,'Financial Statement'!B62<'Financial 40'!L54,'Financial Statement'!B62>='Financial 40'!K54),'Financial 40'!O54, IF(AND('Data Validation'!C4='Financial 40'!K3,'Financial Statement'!B62<'Financial 40'!L55,'Financial Statement'!B62>='Financial 40'!K55),'Financial 40'!O55, IF(AND('Data Validation'!C4='Financial 40'!K3,'Financial Statement'!B62<'Financial 40'!L56,'Financial Statement'!B62>='Financial 40'!K56),'Financial 40'!O56, IF(AND('Data Validation'!C4='Financial 40'!K3,'Financial Statement'!B62<'Financial 40'!L57),'Financial 40'!O57, IF(AND('Data Validation'!C4='Financial 40'!M3,'Financial Statement'!B62>='Financial 40'!N53),'Financial 40'!O53, IF(AND('Data Validation'!C4='Financial 40'!M3,'Financial Statement'!B62<'Financial 40'!N54,'Financial Statement'!B62>='Financial 40'!M54),'Financial 40'!O54, IF(AND('Data Validation'!C4='Financial 40'!M3,'Financial Statement'!B62<'Financial 40'!N55,'Financial Statement'!B62>='Financial 40'!M55),'Financial 40'!O55, IF(AND('Data Validation'!C4='Financial 40'!M3,'Financial Statement'!B62<'Financial 40'!N56,'Financial Statement'!B62>='Financial 40'!M56),'Financial 40'!O56, IF(AND('Data Validation'!C4='Financial 40'!M3,'Financial Statement'!B62<'Financial 40'!N57),'Financial 40'!O57)))))))))))))))))))))))))))))) -> #DIV/0!
A16: Industry Outlook (7%) | B16: Business/Industry outlook of the customer | C16: ='Industry attractiveness 7'!E4 -> 0.02 | D16: =IF('Data Validation'!C12='Industry attractiveness 7'!D4,'Industry attractiveness 7'!E4, IF('Data Validation'!C12='Industry attractiveness 7'!D5,'Industry attractiveness 7'!E5, IF('Data Validation'!C12='Industry attractiveness 7'!D6,'Industry attractiveness 7'!E6))) -> FALSE | F16: =SUM(D16:D18) -> 0
B17: Market competition | C17: ='Industry attractiveness 7'!E7 -> 0.03 | D17: =IF('Data Validation'!C13='Industry attractiveness 7'!D7,'Industry attractiveness 7'!E7, IF('Data Validation'!C13='Industry attractiveness 7'!D9,'Industry attractiveness 7'!E9, IF('Data Validation'!C13='Industry attractiveness 7'!D10,'Industry attractiveness 7'!E10))) -> FALSE
B18: Form of Organization | C18: ='Industry attractiveness 7'!E11 -> 0.02 | D18: =IF('Data Validation'!C14='Industry attractiveness 7'!D11,'Industry attractiveness 7'!E11, IF('Data Validation'!C14='Industry attractiveness 7'!D12,'Industry attractiveness 7'!E12, IF('Data Validation'!C14='Industry attractiveness 7'!D13,'Industry attractiveness 7'!E13, IF('Data Validation'!C14='Industry attractiveness 7'!D14,'Industry attractiveness 7'!E14)))) -> FALSE
A19: Credit History (29%) | B19: OD Classification | C19: ='Credit History 29'!F4 -> 0.04 | D19: =IF('Data Validation'!C30="NO","", IF(AND('Data Validation'!C35='Credit History 29'!E4,'Data Validation'!C30="YES"),'Credit History 29'!F4, IF(AND('Data Validation'!C35='Credit History 29'!E5,'Data Validation'!C30="YES"),'Credit History 29'!F5, IF(AND('Data Validation'!C35='Credit History 29'!E6,'Data Validation'!C30="YES"),'Credit History 29'!F6, IF(AND('Data Validation'!C35='Credit History 29'!E7,'Data Validation'!C30="YES"),'Credit History 29'!F7, IF(AND('Data Validation'!C35='Credit History 29'!E8,'Data Validation'!C30="YES"),'Credit History 29'!F8)))))) | E19: =IF('Data Validation'!C30="YES",SUM(D19:D22),"") | F19: =IF(SUM(E19:E30)=0,"",AVERAGE(E19:E30))
B20: OD Swing Highest Debit | C20: ='Credit History 29'!F10 -> 0.03 | D20: =IF('Data Validation'!C30="NO","", IF(AND('Data Validation'!C32>='Credit History 29'!D11,'Data Validation'!C32<'Credit History 29'!E11,'Data Validation'!C30="YES"),'Credit History 29'!F11, IF(AND('Data Validation'!C32<'Credit History 29'!E12,'Data Validation'!C30="YES"),'Credit History 29'!F12, IF(AND('Data Validation'!C32>='Credit History 29'!E10,'Data Validation'!C30="YES"),'Credit History 29'!F10))))
B21: OD Swing Lowest Debit | C21: ='Credit History 29'!F13 -> 0.04 | D21: =IF('Data Validation'!C30="NO","", IF(AND('Data Validation'!C33<='Credit History 29'!E13,'Data Validation'!C30="YES"),'Credit History 29'!F13, IF(AND('Data Validation'!C33<='Credit History 29'!D14,'Data Validation'!C33>'Credit History 29'!E14,'Data Validation'!C30="YES"),'Credit History 29'!F14, IF(AND('Data Validation'!C33>'Credit History 29'!E15,'Data Validation'!C30="YES"),'Credit History 29'!F15))))
B22: OD Turnover | C22: ='Credit History 29'!F16 -> 0.1 | D22: =IF('Data Validation'!C30="NO","", IF(AND('Data Validation'!C34>='Credit History 29'!E16,'Data Validation'!C30="YES"),'Credit History 29'!F16, IF(AND('Data Validation'!C34>='Credit History 29'!D17,'Data Validation'!C34<'Credit History 29'!E17,'Data Validation'!C30="YES"),'Credit History 29'!F17, IF(AND('Data Validation'!C34>='Credit History 29'!D18,'Data Validation'!C34<'Credit History 29'!E18,'Data Validation'!C30="YES"),'Credit History 29'!F18, IF(AND('Data Validation'!C34<'Credit History 29'!E19,'Data Validation'!C30="YES"),'Credit History 29'!F19)))))
B23: Existing T/L Repayment | C23: ='Credit History 29'!F21 -> 0.21 | D23: =IF(OR('Data Validation'!C50="NO",'Data Validation'!C50=""),"", IF(AND('Data Validation'!C51='Credit History 29'!E21,'Data Validation'!C50="YES"),'Credit History 29'!F21, IF(AND('Data Validation'!C51='Credit History 29'!E22,'Data Validation'!C50="YES"),'Credit History 29'!F22, IF(AND('Data Validation'!C51='Credit History 29'!E23,'Data Validation'!C50="YES"),'Credit History 29'!F23, IF(AND('Data Validation'!C51='Credit History 29'!E24,'Data Validation'!C50="YES"),'Credit History 29'!F24))))) | E23: =IF('Data Validation'!C50="YES",SUM(D23),"")
B24: Average settlement of import L/C facility | C24: ='Credit History 29'!F26 -> 0.21 | D24: =IF(OR('Data Validation'!C36="NO",'Data Validation'!C36=""),"", IF(AND('Data Validation'!C37='Credit History 29'!E26,'Data Validation'!C36="YES"),'Credit History 29'!F26, IF(AND('Data Validation'!C37='Credit History 29'!E27,'Data Validation'!C36="YES"),'Credit History 29'!F27, IF(AND('Data Validation'!C37='Credit History 29'!E28,'Data Validation'!C36="YES"),'Credit History 29'!F28, IF(AND('Data Validation'!C37='Credit History 29'!E29,'Data Validation'!C36="YES"),'Credit History 29'!F29))))) | E24: =IF('Data Validation'!C36="YES",SUM(D24),"")
B25: Settlement of Merchandise Loan | C25: ='Credit History 29'!F31 -> 0.08 | D25: =IF(OR('Data Validation'!C38="NO",'Data Validation'!C38=""),"", IF(AND('Data Validation'!C40='Credit History 29'!E31,'Data Validation'!C38="YES"),'Credit History 29'!F31, IF(AND('Data Validation'!C40='Credit History 29'!E32,'Data Validation'!C38="YES"),'Credit History 29'!F32, IF(AND('Data Validation'!C40='Credit History 29'!E33,'Data Validation'!C38="YES"),'Credit History 29'!F33, IF(AND('Data Validation'!C40='Credit History 29'!E34,'Data Validation'!C38="YES"),'Credit History 29'!F34))))) | E25: =IF('Data Validation'!C38="YES",SUM(D25:D26),"")
B26: Merchandise Turn-over | C26: ='Credit History 29'!F35 -> 0.13 | D26: =IF(OR('Data Validation'!C38="NO",'Data Validation'!C38=""),"", IF(AND('Data Validation'!C41>='Credit History 29'!E35,'Data Validation'!C38="YES"),'Credit History 29'!F35, IF(AND('Data Validation'!C41>='Credit History 29'!D36,'Data Validation'!C41<'Credit History 29'!E36,'Data Validation'!C38="YES"),'Credit History 29'!F36, IF(AND('Data Validation'!C41>='Credit History 29'!D37,'Data Validation'!C41<'Credit History 29'!E37,'Data Validation'!C38="YES"),'Credit History 29'!F37, IF(AND('Data Validation'!C41>='Credit History 29'!D38,'Data Validation'!C41<'Credit History 29'!E38,'Data Validation'!C38="YES"),'Credit History 29'!F38, IF(AND('Data Validation'!C41<'Credit History 29'!E39,'Data Validation'!C38="YES"),'Credit History 29'!F39))))))
B27: Settlement of Pre-Shipment Loan | C27: ='Credit History 29'!F41 -> 0.08 | D27: =IF(OR('Data Validation'!C42="NO",'Data Validation'!C42=""),"", IF(AND('Data Validation'!C44='Credit History 29'!E41,'Data Validation'!C42="YES"),'Credit History 29'!F41, IF(AND('Data Validation'!C44='Credit History 29'!E42,'Data Validation'!C42="YES"),'Credit History 29'!F42, IF(AND('Data Validation'!C44='Credit History 29'!E43,'Data Validation'!C42="YES"),'Credit History 29'!F43, IF(AND('Data Validation'!C44='Credit History 29'!E44,'Data Validation'!C42="YES"),'Credit History 29'!F44))))) | E27: =IF('Data Validation'!C42="YES",SUM(D27:D28),"")
B28: Pre-Shipment Turn-over | C28: ='Credit History 29'!F45 -> 0.13 | D28: =IF(OR('Data Validation'!C42="NO",'Data Validation'!C42=""),"", IF(AND('Data Validation'!C45>='Credit History 29'!E45,'Data Validation'!C42="YES"),'Credit History 29'!F45, IF(AND('Data Validation'!C45>='Credit History 29'!D46,'Data Validation'!C45<'Credit History 29'!E46,'Data Validation'!C42="YES"),'Credit History 29'!F46, IF(AND('Data Validation'!C45>='Credit History 29'!D47,'Data Validation'!C45<'Credit History 29'!E47,'Data Validation'!C42="YES"),'Credit History 29'!F47, IF(AND('Data Validation'!C45>='Credit History 29'!D48,'Data Validation'!C45<'Credit History 29'!E48,'Data Validation'!C42="YES"),'Credit History 29'!F48, IF(AND('Data Validation'!C45>='Credit History 29'!D49,'Data Validation'!C45<'Credit History 29'!E49,'Data Validation'!C42="YES"),'Credit History 29'!F49, IF(AND('Data Validation'!C45<'Credit History 29'!E50,'Data Validation'!C42="YES"),'Credit History 29'!F50)))))))
B29: Post Export Credit facility | C29: ='Credit History 29'!F52 -> 0.21 | D29: =IF(OR('Data Validation'!C46="NO",'Data Validation'!C46=""),"", IF(AND('Data Validation'!C46="YES",'Data Validation'!C47='Credit History 29'!E52),'Credit History 29'!F52, IF(AND('Data Validation'!C46="YES",'Data Validation'!C47='Credit History 29'!E53),'Credit History 29'!F53, IF(AND('Data Validation'!C46="YES",'Data Validation'!C47='Credit History 29'!E54),'Credit History 29'!F54, IF(AND('Data Validation'!C46="YES",'Data Validation'!C47='Credit History 29'!E55),'Credit History 29'!F55, IF(AND('Data Validation'!C46="YES",'Data Validation'!C47='Credit History 29'!E56),'Credit History 29'!F56)))))) | E29: =IF('Data Validation'!C46="YES",SUM(D29),"")
B30: Settlement of Guarantee | C30: ='Credit History 29'!F52 -> 0.21 | D30: =IF(OR('Data Validation'!C48="NO",'Data Validation'!C48=""),"", IF(AND('Data Validation'!C48="YES",'Data Validation'!C49='Credit History 29'!E57),'Credit History 29'!F57, IF(AND('Data Validation'!C48="YES",'Data Validation'!C49='Credit History 29'!E58),'Credit History 29'!F58, IF(AND('Data Validation'!C48="YES",'Data Validation'!C49='Credit History 29'!E59),'Credit History 29'!F59)))) | E30: =IF('Data Validation'!C48="YES",SUM(D30),"")
B31: Settled Term Loans | C31: ='Credit History 29'!F66 -> 0.01 | D31: =IF(OR('Data Validation'!C50="NO",'Data Validation'!C50=""),"", IF('Data Validation'!C52='Credit History 29'!E66,'Credit History 29'!F66, IF('Data Validation'!C52='Credit History 29'!E67,'Credit History 29'!F67, IF('Data Validation'!C52='Credit History 29'!E68,'Credit History 29'!F68, IF('Data Validation'!C52='Credit History 29'!E69,'Credit History 29'!F69))))) | E31: =D31 | F31: =E31
B32: Aggregate Credit Exposure | C32: ='Credit History 29'!F61 -> 0.01 | D32: =IF('Credit Information'!H77+'Credit Information'!H27=0,"", IF('Data Validation'!C54='Credit History 29'!E61,'Credit History 29'!F61, IF('Data Validation'!C54='Credit History 29'!E62,'Credit History 29'!F62, IF('Data Validation'!C54='Credit History 29'!E63,'Credit History 29'!F63, IF('Data Validation'!C54='Credit History 29'!E64,'Credit History 29'!F64))))) | E32: =D32 | F32: =E32
B33: Adverse Classification Ever | C33: ='Credit History 29'!F71 -> 0.02 | D33: =IF(OR('Credit Information'!H77+'Credit Information'!H27=0,'Data Validation'!C55=""),"", IF('Data Validation'!C56='Credit History 29'!E71,'Credit History 29'!F71, IF('Data Validation'!C56='Credit History 29'!E72,'Credit History 29'!F72, IF('Data Validation'!C56='Credit History 29'!E73,'Credit History 29'!F73, IF('Data Validation'!C56='Credit History 29'!E74,'Credit History 29'!F74))))) | E33: =D33 | F33: =E33
B34: ='Credit History 29'!C76 -> Account Transaction vs Outstanding Loan | C34: ='Credit History 29'!F76 -> 0.04 | D34: =IF(OR('Credit Information'!H27=0,'Data Validation'!C29="",'Data Validation'!C29="NO"),"", IF('Data Validation'!C57>='Credit History 29'!E76,'Credit History 29'!F76, IF(AND('Data Validation'!C57>='Credit History 29'!D77,'Data Validation'!C57<'Credit History 29'!E77),'Credit History 29'!F77, IF(AND('Data Validation'!C57>='Credit History 29'!D78,'Data Validation'!C57<'Credit History 29'!E78),'Credit History 29'!F78, IF('Data Validation'!C57<'Credit History 29'!E79,'Credit History 29'!F79))))) | E34: =IF('Credit Information'!I27=0,"",'Business Strength Score'!D34) | F34: =E34
A35: Banking Relationship (10%) | B35: Length of relationship with CBO | C35: ='Banking Relationship 10'!E5 -> 0.03 | D35: =IF('Data Validation'!C59>='Banking Relationship 10'!D5,'Banking Relationship 10'!E5, IF(AND('Data Validation'!C59<'Banking Relationship 10'!D6,'Data Validation'!C59>='Banking Relationship 10'!C6),'Banking Relationship 10'!E6, IF(AND('Data Validation'!C59<'Banking Relationship 10'!D7,'Data Validation'!C59>='Banking Relationship 10'!C7),'Banking Relationship 10'!E7, IF('Data Validation'!C59<='Banking Relationship 10'!D8,'Banking Relationship 10'!E8)))) -> 0.03 | E35: =SUM(D35:D36) -> 0.1 | F35: =E35 -> 0.1
B36: The account transaction to sales percentage share with CBO | C36: ='Banking Relationship 10'!E9 -> 0.07 | D36: =IF('Data Validation'!C60>='Banking Relationship 10'!D9,'Banking Relationship 10'!E9, IF(AND('Data Validation'!C60<'Banking Relationship 10'!D10,'Data Validation'!C60>='Banking Relationship 10'!C10),'Banking Relationship 10'!E10, IF(AND('Data Validation'!C60<'Banking Relationship 10'!D11,'Data Validation'!C60>='Banking Relationship 10'!C11),'Banking Relationship 10'!E11, IF(AND('Data Validation'!C60<'Banking Relationship 10'!D12,'Data Validation'!C60>='Banking Relationship 10'!C12),'Banking Relationship 10'!E12, IF(AND('Data Validation'!C60<'Banking Relationship 10'!D13,'Data Validation'!C60>='Banking Relationship 10'!C13),'Banking Relationship 10'!E13, IF(AND('Data Validation'!C60<'Banking Relationship 10'!D14,'Data Validation'!C60>='Banking Relationship 10'!C14),'Banking Relationship 10'!E14, IF('Data Validation'!C60<='Banking Relationship 10'!D15,'Banking Relationship 10'!E15))))))) -> 0.07
A37: Character of applicant/management (5%) | B37: Consistency of presented document | C37: ='Character 5'!D5 -> 0.02 | D37: =IF('Data Validation'!C62='Character 5'!C5,'Character 5'!D5, IF('Data Validation'!C62='Character 5'!C6,'Character 5'!D6, IF('Data Validation'!C62='Character 5'!C7,'Character 5'!D7))) -> 0.02 | E37: =SUM(D37:D39) -> 0.02 | F37: =E37 -> 0.02
B38: Responsiveness to wards bank's inquiry | C38: ='Character 5'!D8 -> 0.02 | D38: =IF('Data Validation'!C63='Character 5'!C8,'Character 5'!D8, IF('Data Validation'!C63='Character 5'!C9,'Character 5'!D9, IF('Data Validation'!C63='Character 5'!C10,'Character 5'!D10, IF('Data Validation'!C63='Character 5'!C11,'Character 5'!D11)))) -> FALSE
B39: Corporate Responsibility (Tax Payment) | C39: ='Character 5'!D12 -> 0.01 | D39: =IF('Data Validation'!C64='Character 5'!C12,'Character 5'!D12, IF('Data Validation'!C64='Character 5'!C13,'Character 5'!D13, IF('Data Validation'!C64='Character 5'!C14,'Character 5'!D14))) -> FALSE
A40: Management Capacity (9%) | B40: Experience in related Line of Business | C40: ='Management Capacity 9'!E5 -> 0.04 | D40: =IF('Data Validation'!C66='Management Capacity 9'!D5,'Management Capacity 9'!E5, IF('Data Validation'!C66='Management Capacity 9'!D6,'Management Capacity 9'!E6, IF('Data Validation'!C66='Management Capacity 9'!D7,'Management Capacity 9'!E7, IF('Data Validation'!C66='Management Capacity 9'!D8,'Management Capacity 9'!E8)))) -> FALSE | E40: =SUM(D40:D42) -> 0 | F40: =E40 -> 0
B41: Qualification | C41: ='Management Capacity 9'!E9 -> 0.02 | D41: =IF('Data Validation'!C67='Management Capacity 9'!D9,'Management Capacity 9'!E9, IF('Data Validation'!C67='Management Capacity 9'!D10,'Management Capacity 9'!E10, IF('Data Validation'!C67='Management Capacity 9'!D11,'Management Capacity 9'!E11, IF('Data Validation'!C67='Management Capacity 9'!D12,'Management Capacity 9'!E12)))) -> FALSE
B42: Availability of clear duty Segregation | C42: ='Management Capacity 9'!E13 -> 0.03 | D42: =IF('Data Validation'!C68='Management Capacity 9'!D13,'Management Capacity 9'!E13, IF('Data Validation'!C68='Management Capacity 9'!D14,'Management Capacity 9'!E14, IF('Data Validation'!C68='Management Capacity 9'!D15,'Management Capacity 9'!E15))) -> FALSE
A43: Total Business Strength | C43: =IF(OR(SUM(F19:F34)=0,SUM(F19:F34)=""),(F5+F16+F35+F37+F40)/(SUM(C5:C15)+SUM(C16:C18)+SUM(C35:C36)+SUM(C37:C39)+SUM(C40:C42)),SUM(F5:F42)) -> #DIV/0!
A44: ='Business Strength Grade'!D3 -> Business Strength Grade | C44: =IF(C43>='Business Strength Grade'!B4,'Business Strength Grade'!D4, IF(AND(C43>='Business Strength Grade'!B5,C43<'Business Strength Grade'!C5),'Business Strength Grade'!D5, IF(AND(C43>='Business Strength Grade'!B6,C43<'Business Strength Grade'!C6),'Business Strength Grade'!D6, IF(AND(C43>='Business Strength Grade'!B7,C43<'Business Strength Grade'!C7),'Business Strength Grade'!D7, IF(C43<'Business Strength Grade'!C8,'Business Strength Grade'!D8))))) -> #DIV/0!
A45: ='Business Strength Grade'!E3 -> Business Risk Level | C45: =IF(C44='Business Strength Grade'!D4,'Business Strength Grade'!E4, IF(C44='Business Strength Grade'!D5,'Business Strength Grade'!E5, IF(C44='Business Strength Grade'!D6,'Business Strength Grade'!E6, IF(C44='Business Strength Grade'!D7,'Business Strength Grade'!E7, IF(C44='Business Strength Grade'!D8,'Business Strength Grade'!E8))))) -> #DIV/0!
A46: ='Business Strength Grade'!F3 -> Bankability | C46: =IF(C44='Business Strength Grade'!D4,'Business Strength Grade'!F4, IF(C44='Business Strength Grade'!D5,'Business Strength Grade'!F5, IF(C44='Business Strength Grade'!D6,'Business Strength Grade'!F6, IF(C44='Business Strength Grade'!D7,'Business Strength Grade'!F7, IF(C44='Business Strength Grade'!D8,'Business Strength Grade'!F8))))) -> #DIV/0!
A47: Collateral Type | C47: ='Security Related Factor'!E5 -> 0.2 | D47: =IF(AND('Data Validation'!C74="YES",'Data Validation'!C75='Security Related Factor'!D5),'Security Related Factor'!E5, IF(AND('Data Validation'!C74="YES",'Data Validation'!C75='Security Related Factor'!D6),'Security Related Factor'!E6, IF(AND('Data Validation'!C74="YES",'Data Validation'!C75='Security Related Factor'!D7),'Security Related Factor'!E7, IF(AND('Data Validation'!C74="YES",'Data Validation'!C75='Security Related Factor'!D8),'Security Related Factor'!E8, IF(AND('Data Validation'!C74="YES",'Data Validation'!C75='Security Related Factor'!D9),'Security Related Factor'!E9, IF(AND('Data Validation'!C74="YES",'Data Validation'!C75='Security Related Factor'!D10),'Security Related Factor'!E10, IF(AND('Data Validation'!C74="YES",'Data Validation'!C75='Security Related Factor'!D11),'Security Related Factor'!E11, IF(AND('Data Validation'!C74="YES",'Data Validation'!C75='Security Related Factor'!D12),'Security Related Factor'!E12, IF(AND('Data Validation'!C74="YES",'Data Validation'!C75='Security Related Factor'!D13),'Security Related Factor'!E13, IF(AND('Data Validation'!C74="YES",'Data Validation'!C75='Security Related Factor'!D14),'Security Related Factor'!E14, IF(AND('Data Validation'!C74="YES",'Data Validation'!C75='Security Related Factor'!D15),'Security Related Factor'!E15, IF(AND('Data Validation'!C74="YES",'Data Validation'!C75='Security Related Factor'!D16),'Security Related Factor'!E16, IF(AND('Data Validation'!C74="YES",'Data Validation'!C75='Security Related Factor'!D17),'Security Related Factor'!E17, IF(AND('Data Validation'!C74="YES",'Data Validation'!C75='Security Related Factor'!D18),'Security Related Factor'!E18, IF(AND('Data Validation'!C74="YES",'Data Validation'!C75='Security Related Factor'!D18),'Security Related Factor'!E18))))))))))))))) -> FALSE | E47: =SUM(D47:D48) -> 0 | F47: =D47+D48 -> 0
A48: Collateral Coverage | C48: ='Security Related Factor'!E20 -> 0.8 | D48: =IF(AND('Data Validation'!C14<>"Cooperatives",'Data Validation'!C74="YES",'Data Validation'!C79>='Security Related Factor'!D20),'Security Related Factor'!E20, IF(AND('Data Validation'!C14<>"Cooperatives",'Data Validation'!C74="YES",'Data Validation'!C79>='Security Related Factor'!C21,'Data Validation'!C79<'Security Related Factor'!D21),'Security Related Factor'!E21, IF(AND('Data Validation'!C14<>"Cooperatives",'Data Validation'!C74="YES",'Data Validation'!C79>='Security Related Factor'!C22,'Data Validation'!C79<'Security Related Factor'!D22),'Security Related Factor'!E22, IF(AND('Data Validation'!C14<>"Cooperatives",'Data Validation'!C74="YES",'Data Validation'!C79>='Security Related Factor'!C23,'Data Validation'!C79<'Security Related Factor'!D23),'Security Related Factor'!E23, IF(AND('Data Validation'!C14<>"Cooperatives",'Data Validation'!C74="YES",'Data Validation'!C79>='Security Related Factor'!C24,'Data Validation'!C79<'Security Related Factor'!D24),'Security Related Factor'!E24, IF(AND('Data Validation'!C14<>"Cooperatives",'Data Validation'!C74="YES",'Data Validation'!C79>='Security Related Factor'!C25,'Data Validation'!C79<'Security Related Factor'!D25),'Security Related Factor'!E25, IF(AND('Data Validation'!C14<>"Cooperatives",'Data Validation'!C74="YES",'Data Validation'!C79>='Security Related Factor'!C26,'Data Validation'!C79<'Security Related Factor'!D26),'Security Related Factor'!E26, IF(AND('Data Validation'!C14<>"Cooperatives",'Data Validation'!C74="YES",'Data Validation'!C79<'Security Related Factor'!D27),'Security Related Factor'!E27, IF(AND('Data Validation'!C14="Cooperatives",'Data Validation'!C74="YES",'Data Validation'!C79>='Security Related Factor'!D47),'Security Related Factor'!E47, IF(AND('Data Validation'!C14="Cooperatives",'Data Validation'!C74="YES",'Data Validation'!C79>='Security Related Factor'!C48,'Data Validation'!C79<'Security Related Factor'!D48),'Security Related Factor'!E48, IF(AND('Data Validation'!C14="Cooperatives",'Data Validation'!C74="YES",'Data Validation'!C79>='Security Related Factor'!C49,'Data Validation'!C79<'Security Related Factor'!D49),'Security Related Factor'!E49, IF(AND('Data Validation'!C14="Cooperatives",'Data Validation'!C74="YES",'Data Validation'!C79>='Security Related Factor'!C50,'Data Validation'!C79<'Security Related Factor'!D50),'Security Related Factor'!E50, IF(AND('Data Validation'!C14="Cooperatives",'Data Validation'!C74="YES",'Data Validation'!C79>='Security Related Factor'!C51,'Data Validation'!C79<'Security Related Factor'!D51),'Security Related Factor'!E51, IF(AND('Data Validation'!C14="Cooperatives",'Data Validation'!C74="YES",'Data Validation'!C79>='Security Related Factor'!C52,'Data Validation'!C79<'Security Related Factor'!D52),'Security Related Factor'!E52, IF(AND('Data Validation'!C14="Cooperatives",'Data Validation'!C74="YES",'Data Validation'!C79<'Security Related Factor'!D53),'Security Related Factor'!E53))))))))))))))) -> FALSE
A49: Collateral Strength | C49: =F47 -> 0
A50: ='Coll Summary'!E2 -> Collateral Strength Grade | C50: =IF(C49>'Coll Summary'!C3,'Coll Summary'!E3, IF(AND(C49>='Coll Summary'!C4,C49<'Coll Summary'!D4),'Coll Summary'!E4, IF(AND(C49>='Coll Summary'!C5,C49<'Coll Summary'!D5),'Coll Summary'!E5, IF(AND(C49>='Coll Summary'!C6,C49<'Coll Summary'!D6),'Coll Summary'!E6, IF(C49<'Coll Summary'!D7,'Coll Summary'!E7))))) -> Unsecured
A51: ='Coll Summary'!F2 -> Collateral Risk Level | C51: =IF(C49>'Coll Summary'!C3,'Coll Summary'!F3, IF(AND(C49>='Coll Summary'!C4,C49<'Coll Summary'!D4),'Coll Summary'!F4, IF(AND(C49>='Coll Summary'!C5,C49<'Coll Summary'!D5),'Coll Summary'!F5, IF(AND(C49>='Coll Summary'!C6,C49<'Coll Summary'!D6),'Coll Summary'!F6, IF(C49<'Coll Summary'!D7,'Coll Summary'!F7))))) -> Very high risk
A52: Risk Matrix | C52: =IF(AND(C46='Coll Summary'!C15,'Business Strength Score'!C50='Coll Summary'!B16),'Coll Summary'!C16, IF(AND(C46='Coll Summary'!C15,'Business Strength Score'!C50='Coll Summary'!B17),'Coll Summary'!C17, IF(AND(C46='Coll Summary'!C15,'Business Strength Score'!C50='Coll Summary'!B18),'Coll Summary'!C18, IF(AND(C46='Coll Summary'!C15,'Business Strength Score'!C50='Coll Summary'!B19),'Coll Summary'!C19, IF(AND(C46='Coll Summary'!C15,'Business Strength Score'!C50='Coll Summary'!B20),'Coll Summary'!C20, IF(AND(C46='Coll Summary'!D15,'Business Strength Score'!C50='Coll Summary'!B16),'Coll Summary'!D16, IF(AND(C46='Coll Summary'!D15,'Business Strength Score'!C50='Coll Summary'!B17),'Coll Summary'!D17, IF(AND(C46='Coll Summary'!D15,'Business Strength Score'!C50='Coll Summary'!B18),'Coll Summary'!D18, IF(AND(C46='Coll Summary'!D15,'Business Strength Score'!C50='Coll Summary'!B19),'Coll Summary'!D19, IF(AND(C46='Coll Summary'!D15,'Business Strength Score'!C50='Coll Summary'!B20),'Coll Summary'!D20, IF(AND(C46='Coll Summary'!E15,'Business Strength Score'!C50='Coll Summary'!B16),'Coll Summary'!E16, IF(AND(C46='Coll Summary'!E15,'Business Strength Score'!C50='Coll Summary'!B17),'Coll Summary'!E17, IF(AND(C46='Coll Summary'!E15,'Business Strength Score'!C50='Coll Summary'!B18),'Coll Summary'!E18, IF(AND(C46='Coll Summary'!E15,'Business Strength Score'!C50='Coll Summary'!B19),'Coll Summary'!E19, IF(AND(C46='Coll Summary'!E15,'Business Strength Score'!C50='Coll Summary'!B20),'Coll Summary'!E20, IF(AND(C46='Coll Summary'!F15,'Business Strength Score'!C50='Coll Summary'!B16),'Coll Summary'!F16, IF(AND(C46='Coll Summary'!F15,'Business Strength Score'!C50='Coll Summary'!B17),'Coll Summary'!F17, IF(AND(C46='Coll Summary'!F15,'Business Strength Score'!C50='Coll Summary'!B18),'Coll Summary'!F18, IF(AND(C46='Coll Summary'!F15,'Business Strength Score'!C50='Coll Summary'!B19),'Coll Summary'!F19, IF(AND(C46='Coll Summary'!F15,'Business Strength Score'!C50='Coll Summary'!B20),'Coll Summary'!F20, IF(AND(C46='Coll Summary'!G15,'Business Strength Score'!C50='Coll Summary'!B16),'Coll Summary'!G16, IF(AND(C46='Coll Summary'!G15,'Business Strength Score'!C50='Coll Summary'!B17),'Coll Summary'!G17, IF(AND(C46='Coll Summary'!G15,'Business Strength Score'!C50='Coll Summary'!B18),'Coll Summary'!G18, IF(AND(C46='Coll Summary'!G15,'Business Strength Score'!C50='Coll Summary'!B19),'Coll Summary'!G19, IF(AND(C46='Coll Summary'!G15,'Business Strength Score'!C50='Coll Summary'!B20),'Coll Summary'!G20))))))))))))))))))))))))) -> #DIV/0!
A53: Credit Risk Grade | C53: =VLOOKUP(C52,Interpretation!B3:C12,2,0) -> #DIV/0!
A54: Recommended Loan Amount | C54: {=IF(OR('Credit Information'!J31:J77="Substandard",'Credit Information'!J31:J77="Doubtful",'Credit Information'!J31:J77="Loss"),"Not Eligible Due to NPL", IF(C53=Interpretation!C3,Interpretation!D3*'Data Validation'!C73, IF(C53=Interpretation!C4,Interpretation!D4*'Data Validation'!C73, IF(C53=Interpretation!C5,Interpretation!D5*'Data Validation'!C73, IF(C53=Interpretation!C6,Interpretation!D6*'Data Validation'!C73, IF(C53=Interpretation!C7,Interpretation!D7*'Data Validation'!C73, "Not Recommended for Financing"))))))} -> #DIV/0!
A56: Prepared by | B56: ______________________________
A57: Revied by | B57: ______________________________

Sheet Industry attractiveness 7
C2: Industry attractiveness
C3: Measurement | D3: Parameters | E3: Score
B4: Business/Industry and form of organization Risk (7%) | C4: Business/Industry outlook of the customer (3%) | D4: Favorable | E4: 0.02
D5: Stable | E5: 0.01
D6: Unstable | E6: 0
C7: Market competition/market (4%) | D7: Market Leader | E7: 0.03
D8: Market player | E8: 0.02
D9: Average Player | E9: 0.01
D10: Weak Player | E10: 0
C11: Form of Organization (3%) | D11: Cooperatives | E11: 0.02
D12: Share Company | E12: 0.015
D13: Private limited company | E13: 0.01
D14: Sole proprietorship | E14: 0.005
E15: =E4+E7+E11 -> 0.07

Sheet Banking Relationship 10
B3: Banking Relationship (10%)
B4: Measurement | C4: Parameters | E4: Score
B5: Length of relationship with CBO (3%) | D5: 3 | E5: 0.03
C6: 2 | D6: 3 | E6: 0.02
C7: 1 | D7: =C6 -> 2 | E7: 0.01
D8: =C7 -> 1 | E8: 0
B9: The account transaction to sales percentage share with CBO (7%) | D9: 1 | E9: 0.07
C10: 0.9 | D10: 1 | E10: 0.06
C11: 0.8 | D11: =C10 -> 0.9 | E11: 0.05
C12: 0.7 | D12: =C11 -> 0.8 | E12: 0.04
C13: 0.6 | D13: =C12 -> 0.7 | E13: 0.03
C14: 0.5 | D14: =C13 -> 0.6 | E14: 0.02
D15: =C14 -> 0.5 | E15: 0.01
E16: =E9+E5 -> 0.1

Sheet Character 5
B3: Character of applicant/management (5%)
B4: Measurement | C4: Parameters | D4: Score
B5: Consistency of presented document (2%) | C5: Adequate | D5: 0.02
C6: Acceptable | D6: 0.01
C7: Inconsistent | D7: 0
B8: Responsiveness towards bank's inquiry (2%) | C8: Provides consistently prompt | D8: 0.02
C9: Response and willingly | D9: 0.015
C10: Responds with repeated Inquiry | D10: 0.01
C11: Not responsive or willing | D11: 0
B12: Corporate Responsibility (Tax Payment) (1%) | C12: Good | D12: 0.01
C13: Acceptable | D13: 0.005
C14: Inconsistent | D14: 0
D15: =D5+D8+D12 -> 0.05
C16: =7+10+5+40+29+9 -> 100

Sheet Financial 40
B2: Risk Aspects | C2: Sector
C3: Manufacturing | E3: Agriculture | G3: DTS | I3: Import | K3: Export | M3: Construction & Machinery | O3: Score
B4: Financial Position (40%)
B5: Activity Ratio (3%) | D5: 0.3 | F5: 0.3 | H5: 0.3 | J5: 0.3 | L5: 0.3 | N5: 0.3 | O5: 0.03
C6: 0.2 | D6: =D5 -> 0.3 | E6: 0.2 | F6: =F5 -> 0.3 | G6: 0.2 | H6: =H5 -> 0.3 | I6: 0.2 | J6: =J5 -> 0.3 | K6: 0.2 | L6: =L5 -> 0.3 | M6: 0.2 | N6: =N5 -> 0.3 | O6: 0.02
C7: 0.1 | D7: =C6 -> 0.2 | E7: 0.1 | F7: =E6 -> 0.2 | G7: 0.1 | H7: =G6 -> 0.2 | I7: 0.1 | J7: =I6 -> 0.2 | K7: 0.1 | L7: =K6 -> 0.2 | M7: 0.1 | N7: =M6 -> 0.2 | O7: 0.01
D8: =C7 -> 0.1 | F8: =E7 -> 0.1 | H8: =G7 -> 0.1 | J8: =I7 -> 0.1 | L8: =K7 -> 0.1 | N8: =M7 -> 0.1 | O8: 0
B9: Leverage (Total Debt to total asset) 6% | D9: 0.6 | F9: 0.6 | H9: 0.6 | J9: 0.6 | L9: 0.6 | N9: 0.6 | O9: 0.06
C10: 0.7 | D10: 0.6 | E10: 0.7 | F10: 0.6 | G10: 0.7 | H10: 0.6 | I10: 0.7 | J10: 0.6 | K10: 0.7 | L10: 0.6 | M10: 0.7 | N10: 0.6 | O10: 0.04
C11: 0.9 | D11: =C10 -> 0.7 | E11: 0.9 | F11: =E10 -> 0.7 | G11: 0.9 | H11: =G10 -> 0.7 | I11: 0.9 | J11: =I10 -> 0.7 | K11: 0.9 | L11: =K10 -> 0.7 | M11: 0.9 | N11: =M10 -> 0.7 | O11: 0.02
D12: 0.9 | F12: 0.9 | H12: 0.9 | J12: 0.9 | L12: 0.9 | N12: 0.9 | O12: 0
B13: Liquidity (Current Ratio = CA/CL) 5% | D13: 2 | F13: 2 | H13: 2 | J13: 2 | L13: 2 | N13: 2 | O13: 0.05
C14: 1.5 | D14: 2 | E14: 1.5 | F14: 2 | G14: 1.5 | H14: 2 | I14: 1.5 | J14: 2 | K14: 1.5 | L14: 2 | M14: 1.5 | N14: 2 | O14: 0.04
C15: 1 | D15: 1.5 | E15: 1 | F15: 1.5 | G15: 1 | H15: 1.5 | I15: 1 | J15: 1.5 | K15: 1 | L15: 1.5 | M15: 1 | N15: 1.5 | O15: 0.03
C16: 0.5 | D16: 1 | E16: 0.5 | F16: 1 | G16: 0.5 | H16: 1 | I16: 0.5 | J16: 1 | K16: 0.5 | L16: 1 | M16: 0.5 | N16: 1 | O16: 0.02
D17: 0.5 | F17: 0.5 | H17: 0.5 | J17: 0.5 | L17: 0.5 | N17: 0.5 | O17: 0
B18: Profitability
B19: Return on Asset =Net Income after tax /Total asset) 3% | D19: 0.05 | F19: 0.05 | H19: 0.05 | J19: 0.05 | L19: 0.05 | N19: 0.05 | O19: 0.03
C20: 0.03 | D20: 0.05 | E20: 0.03 | F20: 0.05 | G20: 0.03 | H20: 0.05 | I20: 0.03 | J20: 0.05 | K20: 0.03 | L20: 0.05 | M20: 0.03 | N20: 0.05 | O20: 0.02
C21: 0.01 | D21: =C20 -> 0.03 | E21: 0.01 | F21: =E20 -> 0.03 | G21: 0.01 | H21: =G20 -> 0.03 | I21: 0.01 | J21: =I20 -> 0.03 | K21: 0.01 | L21: =K20 -> 0.03 | M21: 0.01 | N21: =M20 -> 0.03 | O21: 0.01
D22: =C21 -> 0.01 | F22: =E21 -> 0.01 | H22: =G21 -> 0.01 | J22: =I21 -> 0.01 | L22: =K21 -> 0.01 | N22: =M21 -> 0.01 | O22: 0
B25: Operating profit Margin(Operating profit/Total Sales) 5% | D25: 0.2 | F25: 0.2 | H25: 0.2 | J25: 0.2 | L25: 0.2 | N25: 0.2 | O25: 0.05
C26: 0.15 | D26: 0.2 | E26: 0.15 | F26: 0.2 | G26: 0.15 | H26: 0.2 | I26: 0.15 | J26: 0.2 | K26: 0.15 | L26: 0.2 | M26: 0.15 | N26: 0.2 | O26: 0.04
C27: 0.1 | D27: 0.15 | E27: 0.1 | F27: 0.15 | G27: 0.1 | H27: 0.15 | I27: 0.1 | J27: 0.15 | K27: 0.1 | L27: 0.15 | M27: 0.1 | N27: 0.15 | O27: 0.03
C28: 0.05 | D28: 0.1 | E28: 0.05 | F28: 0.1 | G28: 0.05 | H28: 0.1 | I28: 0.05 | J28: 0.1 | K28: 0.05 | L28: 0.1 | M28: 0.05 | N28: 0.1 | O28: 0.02
C29: 0 | D29: 0.05 | E29: 0 | F29: 0.05 | G29: 0 | H29: 0.05 | I29: 0 | J29: 0.05 | K29: 0 | L29: 0.05 | M29: 0 | N29: 0.05 | O29: 0.01
B30: Interest Coverage Ratio (Net income after tax/Interest expenses) 3% | D30: 3 | F30: 3 | H30: 3 | J30: 3 | L30: 3 | N30: 3 | O30: 0.03
C31: 2.5 | D31: 3 | E31: 2.5 | F31: 3 | G31: 2.5 | H31: 3 | I31: 2.5 | J31: 3 | K31: 2.5 | L31: 3 | M31: 2.5 | N31: 3 | O31: 0.02
C32: 2 | D32: =C31 -> 2.5 | E32: 2 | F32: =E31 -> 2.5 | G32: 2 | H32: =G31 -> 2.5 | I32: 2 | J32: =I31 -> 2.5 | K32: 2 | L32: =K31 -> 2.5 | M32: 2 | N32: =M31 -> 2.5 | O32: 0.01
D33: =C32 -> 2 | F33: =E32 -> 2 | H33: =G32 -> 2 | J33: =I32 -> 2 | L33: =K32 -> 2 | N33: =M32 -> 2 | O33: 0
F34: 0.5 | H34: 1 | J34: 1 | L34: 0.5 | N34: 0.5 | O34: 0
B35: Inventory Turnover Ratio (CGS/Average Inventory) 4% | D35: 12 | F35: 12 | H35: 12 | J35: 12 | L35: 12 | N35: 12 | O35: 0.04
C36: 9 | D36: 12 | E36: 9 | F36: 12 | G36: 9 | H36: 12 | I36: 9 | J36: 12 | K36: 9 | L36: 12 | M36: 9 | N36: 12 | O36: 0.03
C37: 6 | D37: =C36 -> 9 | E37: 6 | F37: =E36 -> 9 | G37: 6 | H37: =G36 -> 9 | I37: 6 | J37: =I36 -> 9 | K37: 6 | L37: =K36 -> 9 | M37: 6 | N37: =M36 -> 9 | O37: 0.02
C38: 3 | D38: =C37 -> 6 | E38: 3 | F38: =E37 -> 6 | G38: 3 | H38: =G37 -> 6 | I38: 3 | J38: =I37 -> 6 | K38: 3 | L38: =K37 -> 6 | M38: 3 | N38: =M37 -> 6 | O38: 0.01
D39: =C38 -> 3 | F39: =E38 -> 3 | H39: =G38 -> 3 | J39: =I38 -> 3 | L39: =K38 -> 3 | N39: =M38 -> 3 | O39: 0
B40: Return on Equity (Net Income / Equity) 4% | D40: 0.2 | F40: 0.2 | H40: 0.2 | J40: 0.2 | L40: 0.2 | N40: 0.2 | O40: 0.04
C41: 0.15 | D41: =D40 -> 0.2 | E41: 0.15 | F41: =F40 -> 0.2 | G41: 0.15 | H41: =H40 -> 0.2 | I41: 0.15 | J41: =J40 -> 0.2 | K41: 0.15 | L41: =L40 -> 0.2 | M41: 0.15 | N41: =N40 -> 0.2 | O41: 0.03
C42: 0.1 | D42: =C41 -> 0.15 | E42: 0.1 | F42: =E41 -> 0.15 | G42: 0.1 | H42: =G41 -> 0.15 | I42: 0.1 | J42: =I41 -> 0.15 | K42: 0.1 | L42: =K41 -> 0.15 | M42: 0.1 | N42: =M41 -> 0.15 | O42: 0.02
C43: 0.05 | D43: =C42 -> 0.1 | E43: 0.05 | F43: =E42 -> 0.1 | G43: 0.05 | H43: =G42 -> 0.1 | I43: 0.05 | J43: =I42 -> 0.1 | K43: 0.05 | L43: =K42 -> 0.1 | M43: 0.05 | N43: =M42 -> 0.1 | O43: 0.01
D44: =C43 -> 0.05 | F44: =E43 -> 0.05 | H44: =G43 -> 0.05 | J44: =I43 -> 0.05 | L44: =K43 -> 0.05 | N44: =M43 -> 0.05 | O44: 0
B45: Quality of Financial Statement 5%
B46: Quality of Financial Statement 5% | C46: All Audited up to date | O46: 0.02
C47: All Audited and one year provisional statements | O47: 0.01
C48: All provisional statements | O48: 0.005
C49: Commercial Credit Report | O49: 0
B50: Negative Values | C50: Minor discrepancy | O50: -0.02
C51: Major discrepancy | O51: -0.03
C52: NA | O52: 0
B53: Total Equity/Total Asset (5%) | D53: 0.5 | F53: 0.5 | H53: 0.5 | J53: 0.5 | L53: 0.5 | N53: 0.5 | O53: 0.05
C54: 0.4 | D54: 0.5 | E54: 0.4 | F54: 0.5 | G54: 0.4 | H54: 0.5 | I54: 0.4 | J54: 0.5 | K54: 0.4 | L54: 0.5 | M54: 0.4 | N54: 0.5 | O54: 0.04
C55: 0.3 | D55: =C54 -> 0.4 | E55: 0.3 | F55: =E54 -> 0.4 | G55: 0.3 | H55: =G54 -> 0.4 | I55: 0.3 | J55: =I54 -> 0.4 | K55: 0.3 | L55: =K54 -> 0.4 | M55: 0.3 | N55: =M54 -> 0.4 | O55: 0.03
C56: 0.2 | D56: =C55 -> 0.3 | E56: 0.2 | F56: =E55 -> 0.3 | G56: 0.2 | H56: =G55 -> 0.3 | I56: 0.2 | J56: =I55 -> 0.3 | K56: 0.2 | L56: =K55 -> 0.3 | M56: 0.2 | N56: =M55 -> 0.3 | O56: 0.02
D57: =C56 -> 0.2 | F57: =E56 -> 0.2 | H57: =G56 -> 0.2 | J57: =I56 -> 0.2 | L57: =K56 -> 0.2 | N57: =M56 -> 0.2 | O57: 0
O58: =O53+O52+O46+O40+O35+O30+O25+O19+O13+O9+O5 -> 0.4

Sheet Credit History 29
B1: S/N | C1: Measurement | E1: Parameters | F1: Score
B2: Credit History 25%
B3: 1 | C3: Overdraft Facility (21%)
C4: Current Status Classification 4% | E4: Pass | F4: 0.04
E5: Special Mention | F5: 0.01
E6: Substandard | F6: 0
E7: Doubtful | F7: 0
E8: Loss | F8: 0
C9: Swing
C10: Highest debit 3% | E10: 0.85 | F10: 0.03
D11: 0.6 | E11: 0.85 | F11: 0.02
E12: 0.6 | F12: 0.01
C13: Lowest debit 4% | E13: 0 | F13: 0.04
D14: 0.04 | E14: 0 | F14: 0.02
E15: 0.04 | F15: 0
C16: Turnover 10% | E16: 4 | F16: 0.1
D17: 2.5 | E17: 4 | F17: 0.07
D18: 1 | E18: 2.5 | F18: 0.03
E19: 1 | F19: 0
B20: 2 | C20: T/Loan Performance (21%)
C21: Existing loan repayment 21% | E21: Regular Repayment | F21: 0.21
E22: 1 - 29 Days in Arrears | F22: 0.1
E23: 30-89 Days in Arrears | F23: 0.03
E24: More than 89 Days in Arrears | F24: 0
B25: 3 | C25: L/C Facility (21%)
C26: Average settlement of import L/C facility (21%) | E26: Settled within a month | F26: 0.21
E27: Settled within two months | F27: 0.1
E28: Settled within three months | F28: 0.03
E29: Settled after three months | F29: 0
B30: 4 | C30: Merchandise Loan Limit - 21%
C31: Settlement of Merchandise Loan 8% | E31: Settled all advances within due date | F31: 0.08
E32: Settled within 1 - 29 days from the due date | F32: 0.04
E33: Settled within 30 - 89 days from the due date | F33: 0.01
E34: Settled after 90 days from the due date | F34: 0
C35: Turn-over (13%) | E35: 3 | F35: 0.13
D36: 2 | E36: 3 | F36: 0.1
D37: 1.25 | E37: 2 | F37: 0.05
D38: 0.5 | E38: 1.25 | F38: 0.01
E39: 0.5 | F39: 0
B40: 5 | C40: Pre-shipment Export Credit (21%)
C41: Settlement of Pre-shipment in FCY (8%) | E41: Settled all advances within due date | F41: 0.08
E42: Settled within 1 - 29 days from the due date | F42: 0.04
E43: Settled within 30 - 89 days from the due date | F43: 0.01
E44: Settled after 90 days from the due date | F44: 0
C45: Turn over (13%) | E45: 2.5 | F45: 0.13
D46: 2 | E46: 2.5 | F46: 0.1
D47: 1.5 | E47: 2 | F47: 0.06
D48: 1.25 | E48: 1.5 | F48: 0.02
D49: 1 | E49: 1.25 | F49: 0.01
E50: 1 | F50: 0
B51: 6 | C51: Post Export Credit facility (21%)
C52: Average settlement (21%) | E52: Settled within two weeks | F52: 0.21
E53: Settled within three weeks | F53: 0.15
E54: Settled within a month | F54: 0.1
E55: Settled after a month | F55: 0.03
B56: 7 | C56: Guarantee Facility (21%)
C57: Settlement of Guarantee | E57: Settled without claim | F57: 0.21
E58: Claimed but settled by customer | F58: 0.1
E59: Claimed and paid by the bank | F59: 0
B60: 8 | C60: Credit Exposure (1%)
C61: Aggregate Credit Exposure (1%) | E61: >5 million | F61: 0.01
E62: 3 - 5 million | F62: 0.0075
E63: 2 - 3 million | F63: 0.005
E64: < 2 million | F64: 0.0025
B65: 9 | C65: Loan Settlemnt (1%)
C66: Settled loans 1% | E66: Settled with Regular Repayment | F66: 0.01
E67: Settled Timely but with an Element of Irregularity | F67: 0.005
E68: Settled before 90 Days after Due Date | F68: 0.0025
E69: Settled after Being NPL and/ or through Foreclosure, Legal Action | F69: 0
B70: 10 | C70: Adverse Classification Ever (2%)
C71: Worst Days in Arrears 2% | E71: O days | F71: 0.02
E72: 1 - 29 days in arrears | F72: 0.015
E73: 30 - 89 days in arrears | F73: 0.01
E74: > 89 days in arrears | F74: 0
B75: 11 | C75: Account Transaction Perforamce
C76: Account Transaction vs Outstanding Loan | E76: 1 | F76: 0.04
D77: 0.75 | E77: =E76 -> 1 | F77: 0.03
D78: 0.5 | E78: =D77 -> 0.75 | F78: 0.02
D79: 0.25 | E79: =D78 -> 0.5 | F79: 0.01
E80: =D79 -> 0.25 | F80: 0

Sheet Management Capacity  9
B3: Management and Ownership Risk (9%)
B4: S/No | C4: Measurement | D4: Parameters | E4: Score
B5: 1 | C5: Experience in related Line of Business (4%) | D5: >10 | E5: 0.04
D6: 7- 10 years | E6: 0.03
D7: 3- 7 Years | E7: 0.02
D8: < 3 years | E8: 0.01
B9: 2 | C9: Qualification (2%) | D9: 51% and above of the top management Members are 1st Degree and above graduates | E9: 0.02
D10: 51% and above of the top management Members are Diplomaand above graduates | E10: 0.015
D11: 51% and above of the top management members are High School and above graduates | E11: 0.01
D12: 51% and above of the top management members are below High School graduates | E12: 0.005
B13: 3 | C13: Availability of clear duty Segregation (3%) | D13: Clear outlined duties and responsibility supported by organizational structure | E13: 0.03
D14: Semi segregated duties and responsibilities supported by organizational structure | E14: 0.02
D15: Unclear duties, responsibilities and control system breached | E15: 0
E16: =E13+E9+E5 -> 0.09

Sheet Security Related Factor
B3: Collateral Risk (100%)
B4: Collateral Type (20%) | D4: Type of collateral | E4: Score
D5: Cash | E5: 0.2
D6: Cash Substitutes | E6: 0.2
D7: Building | E7: 0.18
D8: Share certificate | E8: 0.15
D9: Merchandize | E9: 0.15
D10: Machinery | E10: 0.13
D11: Vehicle | E11: 0.15
D12: Corporate Guarantee | E12: 0.15
D13: Government Guarantee | E13: 0.2
D14: Bank Guarantee | E14: 0.2
D15: Personal Guarantee | E15: 0
D16: Export Document | E16: 0
... D19: Second Degree Mortgage | E19: 0
B20: Collateral to Loan Coverage Ratio (80%) | D20: 1.1 | E20: 0.8
C21: 1 | D21: =D20 -> 1.1 | E21: 0.7
C22: 0.9 | D22: =C21 -> 1 | E22: 0.6
C23: 0.8 | D23: =C22 -> 0.9 | E23: 0.5
C24: 0.7 | D24: =C23 -> 0.8 | E24: 0.4
C25: 0.6 | D25: =C24 -> 0.7 | E25: 0.3
C26: 0.5 | D26: =C25 -> 0.6 | E26: 0.2
D27: =C26 -> 0.5 | E27: 0
B30: Collateral Risk For Cooperatives (100%)
B31: Collateral Type (20%) | D31: Type of collateral | E31: Score
D32: =D5 -> Cash | E32: =E5 -> 0.2
D33: =D6 -> Cash Substitutes | E33: =E6 -> 0.2
D34: =D7 -> Building | E34: =E7 -> 0.18
D35: =D8 -> Share certificate | E35: =E8 -> 0.15
D36: =D9 -> Merchandize | E36: =E9 -> 0.15
D37: =D10 -> Machinery | E37: =E10 -> 0.13
D38: =D11 -> Vehicle | E38: =E11 -> 0.15
D39: =D12 -> Corporate Guarantee | E39: =E12 -> 0.15
D40: =D13 -> Government Guarantee | E40: =E13 -> 0.2
D41: =D14 -> Bank Guarantee | E41: =E14 -> 0.2
D42: =D15 -> Personal Guarantee | E42: =E15 -> 0
D43: =D16 -> Export Document | E43: =E16 -> 0
... D46: =D19 -> Second Degree Mortgage | E46: =E19 -> 0
B47: Collateral to Loan Coverage Ratio (80%) | D47: 0.75 | E47: 0.8
C48: 0.65 | D48: =D47 -> 0.75 | E48: 0.7
C49: 0.55 | D49: =C48 -> 0.65 | E49: 0.6
C50: 0.45 | D50: =C49 -> 0.55 | E50: 0.5
C51: 0.35 | D51: =C50 -> 0.45 | E51: 0.4
C52: 0.25 | D52: =C51 -> 0.35 | E52: 0.3
D53: =C52 -> 0.25 | E53: 0
B54: In addition , the pricing will be different(lower) from other customers

Sheet Business Strength Grade
B3: Range of Achievement | D3: Business Strength Grade | E3: Business Risk Level | F3: Bankability
B4: 0.95 | C4: 1 | D4: I | E4: Exceptionally Low Risk | F4: Excellent (First Class)
B5: 0.8 | C5: =B4 -> 0.95 | D5: II | E5: Very Low Risk | F5: Reliable (Good Standing)
B6: 0.65 | C6: =B5 -> 0.8 | D6: III | E6: Low Risk | F6: Acceptable (Satisfactory)
B7: 0.5 | C7: =B6 -> 0.65 | D7: IV | E7: Moderate Risk | F7: Watch list (Marginal)
C8: =B7 -> 0.5 | D8: V | E8: High Risk | F8: Poor (Distressed Business )

Sheet Coll Summary
B2: Description | C2: Value | E2: Collateral Strength Grade | F2: Collateral Risk Level
B3: Strongly Secured | C3: 0.9 | D3: 1 | E3: =B3 -> Strongly Secured | F3: Vey Low Risk
B4: Fully Secured | C4: 0.8 | D4: =C3 -> 0.9 | E4: =B4 -> Fully Secured | F4: Low risk
B5: Partially Secured | C5: 0.7 | D5: =C4 -> 0.8 | E5: =B5 -> Partially Secured | F5: Moderate risk
B6: Under Secured | C6: 0.5 | D6: =C5 -> 0.7 | E6: =B6 -> Under Secured | F6: High risk
B7: Unsecured | D7: =C6 -> 0.5 | E7: =B7 -> Unsecured | F7: Very high risk
B14: Security Strength \ Borrower Business Strength | C14: Borrower Business Strength
A15: Security Strength | C15: ='Business Strength Grade'!F4 -> Excellent (First Class) | D15: ='Business Strength Grade'!F5 -> Reliable (Good Standing) | E15: ='Business Strength Grade'!F6 -> Acceptable (Satisfactory) | F15: ='Business Strength Grade'!F7 -> Watch list (Marginal) | G15: ='Business Strength Grade'!F8 -> Poor (Distressed Business )
B16: =E3 -> Strongly Secured | C16: AAA | D16: AA | E16: A | F16: BBB | G16: B
B17: =E4 -> Fully Secured | C17: AA | D17: A | E17: BBB | F17: BB | G17: CCC
B18: =E5 -> Partially Secured | C18: A | D18: BBB | E18: BB | F18: CCC | G18: CC
B19: =E6 -> Under Secured | C19: BBB | D19: BB | E19: CCC | F19: CC | G19: C
B20: =E7 -> Unsecured | C20: BB | D20: CCC | E20: CC | F20: C | G20: D

Sheet Interpretation
B2: Risk Mtrix | C2: Risk Grade | D2: Working Capital Score %
B3: AAA | C3: 1 | D3: 1
B4: AA | C4: 2 | D4: 0.9
B5: A | C5: 3 | D5: 0.8
B6: BBB | C6: 4 | D6: 0.7
B7: BB | C7: 5 | D7: 0.6
B8: B | C8: 6
B9: CCC | C9: 7
B10: CC | C10: 8
B11: C | C11: 9
B12: D | C12: 10
